{"layoutParsingResults": [{"prunedResult": {"page_count": null, "width": 2043, "height": 2846, "model_settings": {"use_doc_preprocessor": false, "use_seal_recognition": true, "use_table_recognition": true, "use_formula_recognition": true, "use_chart_recognition": false, "use_region_detection": true, "format_block_content": false, "markdown_ignore_labels": ["number", "footnote", "header", "header_image", "footer", "footer_image", "aside_text"]}, "parsing_res_list": [{"block_label": "paragraph_title", "block_content": "记先祖坟墓序", "block_bbox": [726, 238, 1164, 308], "block_id": 0, "block_order": 1}, {"block_label": "text", "block_content": "始祖流芳公葬西村之西坡下。二世祖忠、三世祖杲，查墓冢，询族老，疑葬西坟。二世祖孝葬西岭。四世祖真金、真银均葬西坟。五世祖三光、三乐均葬西坟。六世祖跃龙葬西坟，起龙、云龙均葬大坪地。七世祖芳葬后沟、芝葬后洼。八世祖吉葬南大坪地，良、祥、十世祖廷用均葬后洼，九世祖允惠、允举，十世祖廷行、廷宾均葬南地。十一世祖林魁葬下南地。火洼、温庄之八世祖槐葬温庄南地。九世祖又葬后沟。南张村之世祖坟在南地。杜窑北门之世祖坟在西庄地。杜窑南门之世祖坟在村西大块地。东张村之世祖坟在西庄地。西孟村、郑窑据说祖坟在北坡门下。其他各门之祖坟，不知者阙之，不详者略之，非惰也，实不敢妄笔也。\n", "block_bbox": [173, 382, 1707, 899], "block_id": 1, "block_order": 2}, {"block_label": "text", "block_content": "一九六二年十二月初三，十五世俊良志", "block_bbox": [918, 919, 1632, 965], "block_id": 2, "block_order": 3}, {"block_label": "paragraph_title", "block_content": "始祖墓碑原文", "block_bbox": [725, 1060, 1159, 1128], "block_id": 3, "block_order": 4}, {"block_label": "text", "block_content": "始祖原籍山西洪洞，明初迁渑坻坞西村，乃家焉。但世远年湮，墓冢虽存，名讳失传，良可慨矣！予小子允惠、允举，恐始祖墓冢之失传，故刻石以志之。", "block_bbox": [175, 1222, 1705, 1337], "block_id": 4, "block_order": 5}, {"block_label": "text", "block_content": "十一世杜含章撰", "block_bbox": [1328, 1357, 1631, 1403], "block_id": 5, "block_order": 6}, {"block_label": "paragraph_title", "block_content": "始祖讳考", "block_bbox": [801, 1497, 1082, 1564], "block_id": 6, "block_order": 7}, {"block_label": "text", "block_content": "据祖爷们传说，始祖由洪洞南迁时，原为梅、良、秀、纲弟兄四人，破锅各执。寇店始祖原名为纲，彼二处始祖何名未知，所以此处未定。\n", "block_bbox": [174, 1658, 1704, 1771], "block_id": 7, "block_order": 8}, {"block_label": "text", "block_content": "一九八八年十五世杜俊英志", "block_bbox": [1110, 1794, 1633, 1839], "block_id": 8, "block_order": 9}, {"block_label": "text", "block_content": "补正：", "block_bbox": [263, 1916, 375, 1960], "block_id": 9, "block_order": 10}, {"block_label": "text", "block_content": "2009年11月，渑池杜氏代表平泉、苏民、建成三人，参加了在河南偃师召开的中华全国杜氏联谊会第二次会议（首次会议于2007年在江西丰城召开）。晤偃师寇店之杜氏代表乃文，查其家谱，知其迁来时为永、长、富、贵弟兄四人破锅，长祖居寇店，其二世为梅、秀、良、纲，方知1988年绳池修谱时所传兄弟四人名讳之误。又，寇店和渑池二地杜氏，均为明洪武初移民，破锅信物也世存祠堂，毁于1958年“大跃进”时，两地似为同祖，但据寇店杜氏谱牒，其祖由陕西渭南迁来。而渑池杜氏，依明代之碑，迁自山西洪洞，二者又不合，则前之“始祖讳考”尽误，录此存疑备考。", "block_bbox": [170, 1976, 1707, 2404], "block_id": 10, "block_order": 11}, {"block_label": "text", "block_content": "二OO九年十二月十八世杜建成识", "block_bbox": [987, 2418, 1639, 2464], "block_id": 11, "block_order": 12}, {"block_label": "aside_text", "block_content": "渑池杜氏宗谱", "block_bbox": [1812, 731, 1889, 1455], "block_id": 12, "block_order": null}, {"block_label": "text", "block_content": "0", "block_bbox": [1824, 2149, 1874, 2222], "block_id": 13, "block_order": 13}], "layout_det_res": {"boxes": [{"cls_id": 2, "label": "text", "score": 0.9789119958877563, "coordinate": [173.3642578125, 382.37164306640625, 1707.01025390625, 899.9657592773438]}, {"cls_id": 2, "label": "text", "score": 0.9760856628417969, "coordinate": [170.2093505859375, 1976.1458740234375, 1707.727294921875, 2404.37158203125]}, {"cls_id": 2, "label": "text", "score": 0.948456346988678, "coordinate": [174.9228515625, 1658.2904052734375, 1704.9794921875, 1771.8443603515625]}, {"cls_id": 2, "label": "text", "score": 0.9459743499755859, "coordinate": [175.34503173828125, 1222.25, 1705.308837890625, 1337.36865234375]}, {"cls_id": 0, "label": "paragraph_title", "score": 0.9201954007148743, "coordinate": [801.33544921875, 1497.316650390625, 1082.74267578125, 1564.865234375]}, {"cls_id": 2, "label": "text", "score": 0.8809112906455994, "coordinate": [918.302490234375, 919.0731201171875, 1632.8408203125, 965.2999267578125]}, {"cls_id": 0, "label": "paragraph_title", "score": 0.8700793385505676, "coordinate": [725.059326171875, 1060.665283203125, 1159.1427001953125, 1128.786376953125]}, {"cls_id": 2, "label": "text", "score": 0.856976330280304, "coordinate": [987.3505859375, 2418.528076171875, 1639.21337890625, 2464.823486328125]}, {"cls_id": 2, "label": "text", "score": 0.8510878086090088, "coordinate": [1110.488037109375, 1794.6788330078125, 1633.731201171875, 1839.4461669921875]}, {"cls_id": 2, "label": "text", "score": 0.8504557609558105, "coordinate": [263.425537109375, 1916.0897216796875, 375.8045654296875, 1960.6907958984375]}, {"cls_id": 2, "label": "text", "score": 0.8158584833145142, "coordinate": [1328.693115234375, 1357.5662841796875, 1631.803466796875, 1403.1883544921875]}, {"cls_id": 0, "label": "paragraph_title", "score": 0.5946035981178284, "coordinate": [726.4793701171875, 238.24571228027344, 1164.4449462890625, 308.9246826171875]}, {"cls_id": 18, "label": "aside_text", "score": 0.5466445684432983, "coordinate": [1812.536865234375, 731.386474609375, 1889.197021484375, 1455.406005859375]}, {"cls_id": 2, "label": "text", "score": 0.4123421609401703, "coordinate": [1824.87451171875, 2149.36376953125, 1874.674072265625, 2222.13818359375]}]}, "overall_ocr_res": {"model_settings": {"use_doc_preprocessor": false, "use_textline_orientation": true}, "dt_polys": [[[729, 237], [1168, 237], [1168, 313], [729, 313]], [[270, 384], [1702, 382], [1702, 429], [270, 431]], [[185, 453], [1703, 450], [1703, 494], [185, 497]], [[183, 519], [1702, 516], [1702, 560], [183, 563]], [[183, 584], [1700, 583], [1700, 630], [183, 631]], [[187, 653], [1701, 650], [1701, 693], [187, 697]], [[184, 721], [1702, 716], [1702, 761], [184, 765]], [[1800, 722], [1899, 722], [1899, 931], [1800, 931]], [[181, 789], [1701, 782], [1701, 829], [182, 835]], [[183, 856], [1147, 853], [1147, 900], [183, 903]], [[924, 924], [1630, 917], [1630, 961], [924, 968]], [[1812, 1033], [1894, 1034], [1892, 1459], [1809, 1459]], [[726, 1058], [1162, 1058], [1162, 1134], [726, 1134]], [[267, 1222], [1705, 1218], [1705, 1272], [267, 1276]], [[182, 1290], [1491, 1291], [1491, 1341], [182, 1340]], [[1333, 1361], [1631, 1359], [1631, 1403], [1333, 1405]], [[800, 1492], [1092, 1494], [1091, 1574], [799, 1572]], [[272, 1660], [1704, 1660], [1704, 1707], [272, 1707]], [[184, 1727], [1189, 1729], [1189, 1774], [184, 1772]], [[1117, 1797], [1631, 1799], [1631, 1840], [1117, 1838]], [[264, 1912], [381, 1912], [381, 1968], [264, 1968]], [[264, 1977], [1703, 1978], [1703, 2026], [264, 2025]], [[184, 2042], [1704, 2042], [1704, 2089], [184, 2089]], [[181, 2103], [1706, 2103], [1706, 2152], [181, 2152]], [[1826, 2147], [1878, 2147], [1878, 2224], [1826, 2224]], [[179, 2164], [1707, 2162], [1707, 2216], [179, 2218]], [[181, 2230], [1706, 2228], [1706, 2276], [181, 2278]], [[179, 2292], [1705, 2289], [1705, 2339], [179, 2342]], [[181, 2354], [1581, 2354], [1581, 2404], [181, 2404]], [[993, 2420], [1636, 2422], [1636, 2467], [993, 2465]]], "text_det_params": {"limit_side_len": 736, "limit_type": "min", "thresh": 0.3, "max_side_limit": 4000, "box_thresh": 0.6, "unclip_ratio": 1.5}, "text_type": "general", "textline_orientation_angles": [0, 0, 0, 0, 0, 0, 0, 0, 0, 0, 0, 0, 0, 0, 0, 0, 0, 0, 0, 0, 0, 0, 0, 0, 0, 0, 0, 0, 0, 0], "text_rec_score_thresh": 0.0, "return_word_box": false, "rec_texts": ["记先祖坟墓序", "始祖流芳公葬西村之西坡下。二世祖忠、三世祖杲，查墓冢，询族老，疑葬西坟。", "二世祖孝葬西岭。四世祖真金、真银均葬西坟。五世祖三光、三乐均葬西坟。六世祖", "跃龙葬西坟，起龙、云龙均葬大坪地。七世祖芳葬后沟、芝葬后洼。八世祖吉葬南大", "坪地，良、祥、十世祖廷用均葬后洼，九世祖允惠、允举，十世祖廷行、廷宾均葬南地。", "十一世祖林魁葬下南地。火洼、温庄之八世祖槐葬温庄南地。九世祖又葬后沟。南", "张村之世祖坟在南地。杜窑北门之世祖坟在西庄地。杜窑南门之世祖坟在村西大块", "渑池", "地。东张村之世祖坟在西庄地。西孟村、郑窑据说祖坟在北坡门下。其他各门之祖", "坟，不知者阙之，不详者略之，非惰也，实不敢妄笔也。", "一九六二年十二月初三，十五世俊良志", "杜氏宗谱", "始祖墓碑原文", "始祖原籍山西洪洞，明初迁渑坻坞西村，乃家焉。但世远年湮，墓冢虽存，名讳", "失传，良可慨矣！予小子允惠、允举，恐始祖墓冢之失传，故刻石以志之。", "十一世杜含章撰", "始祖讳考", "据祖爷们传说，始祖由洪洞南迁时，原为梅、良、秀、纲弟兄四人，破锅各执。寇", "店始祖原名为纲，彼二处始祖何名未知，所以此处未定。", "一九八八年十五世杜俊英志", "补正：", "2009年11月，渑池杜氏代表平泉、苏民、建成三人，参加了在河南偃师召开的", "中华全国杜氏联谊会第二次会议（首次会议于2007年在江西丰城召开）。晤偃师寇", "店之杜氏代表乃文，查其家谱，知其迁来时为永、长、富、贵弟兄四人破锅，长祖居寇", "0", "店，其二世为梅、秀、良、纲，方知1988年绳池修谱时所传兄弟四人名讳之误。又，寇", "店和渑池二地杜氏，均为明洪武初移民，破锅信物也世存祠堂，毁于1958年“大跃", "进”时，两地似为同祖，但据寇店杜氏谱牒，其祖由陕西渭南迁来。而渑池杜氏，依明", "代之碑，迁自山西洪洞，二者又不合，则前之“始祖讳考”尽误，录此存疑备考。", "二OO九年十二月十八世杜建成识"], "rec_scores": [0.9944844841957092, 0.9720724821090698, 0.9918132424354553, 0.9899826049804688, 0.9716845750808716, 0.9904747009277344, 0.9973870515823364, 0.8679261207580566, 0.9902936220169067, 0.9840892553329468, 0.9872220158576965, 0.9923750758171082, 0.9991097450256348, 0.968061625957489, 0.9705101847648621, 0.9990304112434387, 0.9962459206581116, 0.9751724600791931, 0.9802515506744385, 0.9989614486694336, 0.9843398928642273, 0.9719629883766174, 0.9877853393554688, 0.9764965176582336, 0.6508238315582275, 0.9663509130477905, 0.9685912728309631, 0.9664526581764221, 0.9659879207611084, 0.8919126391410828], "rec_polys": [[[729, 237], [1168, 237], [1168, 313], [729, 313]], [[270, 384], [1702, 382], [1702, 429], [270, 431]], [[185, 453], [1703, 450], [1703, 494], [185, 497]], [[183, 519], [1702, 516], [1702, 560], [183, 563]], [[183, 584], [1700, 583], [1700, 630], [183, 631]], [[187, 653], [1701, 650], [1701, 693], [187, 697]], [[184, 721], [1702, 716], [1702, 761], [184, 765]], [[1800, 722], [1899, 722], [1899, 931], [1800, 931]], [[181, 789], [1701, 782], [1701, 829], [182, 835]], [[183, 856], [1147, 853], [1147, 900], [183, 903]], [[924, 924], [1630, 917], [1630, 961], [924, 968]], [[1812, 1033], [1894, 1034], [1892, 1459], [1809, 1459]], [[726, 1058], [1162, 1058], [1162, 1134], [726, 1134]], [[267, 1222], [1705, 1218], [1705, 1272], [267, 1276]], [[182, 1290], [1491, 1291], [1491, 1341], [182, 1340]], [[1333, 1361], [1631, 1359], [1631, 1403], [1333, 1405]], [[800, 1492], [1092, 1494], [1091, 1574], [799, 1572]], [[272, 1660], [1704, 1660], [1704, 1707], [272, 1707]], [[184, 1727], [1189, 1729], [1189, 1774], [184, 1772]], [[1117, 1797], [1631, 1799], [1631, 1840], [1117, 1838]], [[264, 1912], [381, 1912], [381, 1968], [264, 1968]], [[264, 1977], [1703, 1978], [1703, 2026], [264, 2025]], [[184, 2042], [1704, 2042], [1704, 2089], [184, 2089]], [[181, 2103], [1706, 2103], [1706, 2152], [181, 2152]], [[1826, 2147], [1878, 2147], [1878, 2224], [1826, 2224]], [[179, 2164], [1707, 2162], [1707, 2216], [179, 2218]], [[181, 2230], [1706, 2228], [1706, 2276], [181, 2278]], [[179, 2292], [1705, 2289], [1705, 2339], [179, 2342]], [[181, 2354], [1581, 2354], [1581, 2404], [181, 2404]], [[993, 2420], [1636, 2422], [1636, 2467], [993, 2465]]], "rec_boxes": [[729, 237, 1168, 313], [270, 382, 1702, 431], [185, 450, 1703, 497], [183, 516, 1702, 563], [183, 583, 1700, 631], [187, 650, 1701, 697], [184, 716, 1702, 765], [1800, 722, 1899, 931], [181, 782, 1701, 835], [183, 853, 1147, 903], [924, 917, 1630, 968], [1809, 1033, 1894, 1459], [726, 1058, 1162, 1134], [267, 1218, 1705, 1276], [182, 1290, 1491, 1341], [1333, 1359, 1631, 1405], [799, 1492, 1092, 1574], [272, 1660, 1704, 1707], [184, 1727, 1189, 1774], [1117, 1797, 1631, 1840], [264, 1912, 381, 1968], [264, 1977, 1703, 2026], [184, 2042, 1704, 2089], [181, 2103, 1706, 2152], [1826, 2147, 1878, 2224], [179, 2162, 1707, 2218], [181, 2228, 1706, 2278], [179, 2289, 1705, 2342], [181, 2354, 1581, 2404], [993, 2420, 1636, 2467]]}}, "markdown": {"text": "## 记先祖坟墓序\n\n始祖流芳公葬西村之西坡下。二世祖忠、三世祖杲，查墓冢，询族老，疑葬西坟。二世祖孝葬西岭。四世祖真金、真银均葬西坟。五世祖三光、三乐均葬西坟。六世祖跃龙葬西坟，起龙、云龙均葬大坪地。七世祖芳葬后沟、芝葬后洼。八世祖吉葬南大坪地，良、祥、十世祖廷用均葬后洼，九世祖允惠、允举，十世祖廷行、廷宾均葬南地。十一世祖林魁葬下南地。火洼、温庄之八世祖槐葬温庄南地。九世祖又葬后沟。南张村之世祖坟在南地。杜窑北门之世祖坟在西庄地。杜窑南门之世祖坟在村西大块地。东张村之世祖坟在西庄地。西孟村、郑窑据说祖坟在北坡门下。其他各门之祖坟，不知者阙之，不详者略之，非惰也，实不敢妄笔也。\n\n\n\n一九六二年十二月初三，十五世俊良志\n\n## 始祖墓碑原文\n\n始祖原籍山西洪洞，明初迁渑坻坞西村，乃家焉。但世远年湮，墓冢虽存，名讳失传，良可慨矣！予小子允惠、允举，恐始祖墓冢之失传，故刻石以志之。\n\n十一世杜含章撰\n\n## 始祖讳考\n\n据祖爷们传说，始祖由洪洞南迁时，原为梅、良、秀、纲弟兄四人，破锅各执。寇店始祖原名为纲，彼二处始祖何名未知，所以此处未定。\n\n\n\n一九八八年十五世杜俊英志\n\n补正：\n\n2009年11月，渑池杜氏代表平泉、苏民、建成三人，参加了在河南偃师召开的中华全国杜氏联谊会第二次会议（首次会议于2007年在江西丰城召开）。晤偃师寇店之杜氏代表乃文，查其家谱，知其迁来时为永、长、富、贵弟兄四人破锅，长祖居寇店，其二世为梅、秀、良、纲，方知1988年绳池修谱时所传兄弟四人名讳之误。又，寇店和渑池二地杜氏，均为明洪武初移民，破锅信物也世存祠堂，毁于1958年“大跃进”时，两地似为同祖，但据寇店杜氏谱牒，其祖由陕西渭南迁来。而渑池杜氏，依明代之碑，迁自山西洪洞，二者又不合，则前之“始祖讳考”尽误，录此存疑备考。\n\n二OO九年十二月十八世杜建成识\n\n0", "isStart": false, "isEnd": true, "images": {}}, "outputImages": {"layout_det_res": "https://pplines-online.bj.bcebos.com/deploy/official/paddleocr/structure-v3-online//dc44dbde-3d03-4382-b61c-a87811c0d9d9/layout_det_res_0.jpg?authorization=bce-auth-v1%2FALTAKDN8mY5KlNI7zaRpLmOqrw%2F2026-06-19T02%3A01%3A05Z%2F-1%2F%2F744061ae20f302e79a0dad80c1891911abb864f106e2294de59fa357b3424b91", "region_det_res": "https://pplines-online.bj.bcebos.com/deploy/official/paddleocr/structure-v3-online//dc44dbde-3d03-4382-b61c-a87811c0d9d9/region_det_res_0.jpg?authorization=bce-auth-v1%2FALTAKDN8mY5KlNI7zaRpLmOqrw%2F2026-06-19T02%3A01%3A05Z%2F-1%2F%2Fc6bf449ec716d4d8490154c047a3c6c80ae89221a2b149cb625c5a0bdbc91548", "overall_ocr_res": "https://pplines-online.bj.bcebos.com/deploy/official/paddleocr/structure-v3-online//dc44dbde-3d03-4382-b61c-a87811c0d9d9/overall_ocr_res_0.jpg?authorization=bce-auth-v1%2FALTAKDN8mY5KlNI7zaRpLmOqrw%2F2026-06-19T02%3A01%3A05Z%2F-1%2F%2F4663542c07658b9187f6a3d81d64221afb12cb8af1410d37d74918f876a0fc25", "layout_order_res": "https://pplines-online.bj.bcebos.com/deploy/official/paddleocr/structure-v3-online//dc44dbde-3d03-4382-b61c-a87811c0d9d9/layout_order_res_0.jpg?authorization=bce-auth-v1%2FALTAKDN8mY5KlNI7zaRpLmOqrw%2F2026-06-19T02%3A01%3A06Z%2F-1%2F%2Fcd19f63b29c98c4ec6d716d9ff4206c4a8f7baf309beda262cec014368338c12"}, "inputImage": "https://pplines-online.bj.bcebos.com/deploy/official/paddleocr/structure-v3-online//dc44dbde-3d03-4382-b61c-a87811c0d9d9/input_img_0.jpg?authorization=bce-auth-v1%2FALTAKDN8mY5KlNI7zaRpLmOqrw%2F2026-06-19T02%3A01%3A04Z%2F-1%2F%2F47f937b8f60f9b2be8e4360923f97cb994c5592a9fd3c54f60be9f3feb5db938"}], "dataInfo": {"width": 2043, "height": 2846, "type": "image"}, "ocrResults": [{"prunedResult": {"model_settings": {"use_doc_preprocessor": false, "use_textline_orientation": true}, "dt_polys": [[[729, 237], [1168, 237], [1168, 313], [729, 313]], [[270, 384], [1702, 382], [1702, 429], [270, 431]], [[185, 453], [1703, 450], [1703, 494], [185, 497]], [[183, 519], [1702, 516], [1702, 560], [183, 563]], [[183, 584], [1700, 583], [1700, 630], [183, 631]], [[187, 653], [1701, 650], [1701, 693], [187, 697]], [[184, 721], [1702, 716], [1702, 761], [184, 765]], [[1800, 722], [1899, 722], [1899, 931], [1800, 931]], [[181, 789], [1701, 782], [1701, 829], [182, 835]], [[183, 856], [1147, 853], [1147, 900], [183, 903]], [[924, 924], [1630, 917], [1630, 961], [924, 968]], [[1812, 1033], [1894, 1034], [1892, 1459], [1809, 1459]], [[726, 1058], [1162, 1058], [1162, 1134], [726, 1134]], [[267, 1222], [1705, 1218], [1705, 1272], [267, 1276]], [[182, 1290], [1491, 1291], [1491, 1341], [182, 1340]], [[1333, 1361], [1631, 1359], [1631, 1403], [1333, 1405]], [[800, 1492], [1092, 1494], [1091, 1574], [799, 1572]], [[272, 1660], [1704, 1660], [1704, 1707], [272, 1707]], [[184, 1727], [1189, 1729], [1189, 1774], [184, 1772]], [[1117, 1797], [1631, 1799], [1631, 1840], [1117, 1838]], [[264, 1912], [381, 1912], [381, 1968], [264, 1968]], [[264, 1977], [1703, 1978], [1703, 2026], [264, 2025]], [[184, 2042], [1704, 2042], [1704, 2089], [184, 2089]], [[181, 2103], [1706, 2103], [1706, 2152], [181, 2152]], [[1826, 2147], [1878, 2147], [1878, 2224], [1826, 2224]], [[179, 2164], [1707, 2162], [1707, 2216], [179, 2218]], [[181, 2230], [1706, 2228], [1706, 2276], [181, 2278]], [[179, 2292], [1705, 2289], [1705, 2339], [179, 2342]], [[181, 2354], [1581, 2354], [1581, 2404], [181, 2404]], [[993, 2420], [1636, 2422], [1636, 2467], [993, 2465]]], "text_det_params": {"limit_side_len": 736, "limit_type": "min", "thresh": 0.3, "max_side_limit": 4000, "box_thresh": 0.6, "unclip_ratio": 1.5}, "text_type": "general", "textline_orientation_angles": [0, 0, 0, 0, 0, 0, 0, 0, 0, 0, 0, 0, 0, 0, 0, 0, 0, 0, 0, 0, 0, 0, 0, 0, 0, 0, 0, 0, 0, 0], "text_rec_score_thresh": 0.0, "return_word_box": false, "rec_texts": ["记先祖坟墓序", "始祖流芳公葬西村之西坡下。二世祖忠、三世祖杲，查墓冢，询族老，疑葬西坟。", "二世祖孝葬西岭。四世祖真金、真银均葬西坟。五世祖三光、三乐均葬西坟。六世祖", "跃龙葬西坟，起龙、云龙均葬大坪地。七世祖芳葬后沟、芝葬后洼。八世祖吉葬南大", "坪地，良、祥、十世祖廷用均葬后洼，九世祖允惠、允举，十世祖廷行、廷宾均葬南地。", "十一世祖林魁葬下南地。火洼、温庄之八世祖槐葬温庄南地。九世祖又葬后沟。南", "张村之世祖坟在南地。杜窑北门之世祖坟在西庄地。杜窑南门之世祖坟在村西大块", "渑池", "地。东张村之世祖坟在西庄地。西孟村、郑窑据说祖坟在北坡门下。其他各门之祖", "坟，不知者阙之，不详者略之，非惰也，实不敢妄笔也。", "一九六二年十二月初三，十五世俊良志", "杜氏宗谱", "始祖墓碑原文", "始祖原籍山西洪洞，明初迁渑坻坞西村，乃家焉。但世远年湮，墓冢虽存，名讳", "失传，良可慨矣！予小子允惠、允举，恐始祖墓冢之失传，故刻石以志之。", "十一世杜含章撰", "始祖讳考", "据祖爷们传说，始祖由洪洞南迁时，原为梅、良、秀、纲弟兄四人，破锅各执。寇", "店始祖原名为纲，彼二处始祖何名未知，所以此处未定。", "一九八八年十五世杜俊英志", "补正：", "2009年11月，渑池杜氏代表平泉、苏民、建成三人，参加了在河南偃师召开的", "中华全国杜氏联谊会第二次会议（首次会议于2007年在江西丰城召开）。晤偃师寇", "店之杜氏代表乃文，查其家谱，知其迁来时为永、长、富、贵弟兄四人破锅，长祖居寇", "0", "店，其二世为梅、秀、良、纲，方知1988年绳池修谱时所传兄弟四人名讳之误。又，寇", "店和渑池二地杜氏，均为明洪武初移民，破锅信物也世存祠堂，毁于1958年“大跃", "进”时，两地似为同祖，但据寇店杜氏谱牒，其祖由陕西渭南迁来。而渑池杜氏，依明", "代之碑，迁自山西洪洞，二者又不合，则前之“始祖讳考”尽误，录此存疑备考。", "二OO九年十二月十八世杜建成识"], "rec_scores": [0.9944844841957092, 0.9720724821090698, 0.9918132424354553, 0.9899826049804688, 0.9716845750808716, 0.9904747009277344, 0.9973870515823364, 0.8679261207580566, 0.9902936220169067, 0.9840892553329468, 0.9872220158576965, 0.9923750758171082, 0.9991097450256348, 0.968061625957489, 0.9705101847648621, 0.9990304112434387, 0.9962459206581116, 0.9751724600791931, 0.9802515506744385, 0.9989614486694336, 0.9843398928642273, 0.9719629883766174, 0.9877853393554688, 0.9764965176582336, 0.6508238315582275, 0.9663509130477905, 0.9685912728309631, 0.9664526581764221, 0.9659879207611084, 0.8919126391410828], "rec_polys": [[[729, 237], [1168, 237], [1168, 313], [729, 313]], [[270, 384], [1702, 382], [1702, 429], [270, 431]], [[185, 453], [1703, 450], [1703, 494], [185, 497]], [[183, 519], [1702, 516], [1702, 560], [183, 563]], [[183, 584], [1700, 583], [1700, 630], [183, 631]], [[187, 653], [1701, 650], [1701, 693], [187, 697]], [[184, 721], [1702, 716], [1702, 761], [184, 765]], [[1800, 722], [1899, 722], [1899, 931], [1800, 931]], [[181, 789], [1701, 782], [1701, 829], [182, 835]], [[183, 856], [1147, 853], [1147, 900], [183, 903]], [[924, 924], [1630, 917], [1630, 961], [924, 968]], [[1812, 1033], [1894, 1034], [1892, 1459], [1809, 1459]], [[726, 1058], [1162, 1058], [1162, 1134], [726, 1134]], [[267, 1222], [1705, 1218], [1705, 1272], [267, 1276]], [[182, 1290], [1491, 1291], [1491, 1341], [182, 1340]], [[1333, 1361], [1631, 1359], [1631, 1403], [1333, 1405]], [[800, 1492], [1092, 1494], [1091, 1574], [799, 1572]], [[272, 1660], [1704, 1660], [1704, 1707], [272, 1707]], [[184, 1727], [1189, 1729], [1189, 1774], [184, 1772]], [[1117, 1797], [1631, 1799], [1631, 1840], [1117, 1838]], [[264, 1912], [381, 1912], [381, 1968], [264, 1968]], [[264, 1977], [1703, 1978], [1703, 2026], [264, 2025]], [[184, 2042], [1704, 2042], [1704, 2089], [184, 2089]], [[181, 2103], [1706, 2103], [1706, 2152], [181, 2152]], [[1826, 2147], [1878, 2147], [1878, 2224], [1826, 2224]], [[179, 2164], [1707, 2162], [1707, 2216], [179, 2218]], [[181, 2230], [1706, 2228], [1706, 2276], [181, 2278]], [[179, 2292], [1705, 2289], [1705, 2339], [179, 2342]], [[181, 2354], [1581, 2354], [1581, 2404], [181, 2404]], [[993, 2420], [1636, 2422], [1636, 2467], [993, 2465]]], "rec_boxes": [[729, 237, 1168, 313], [270, 382, 1702, 431], [185, 450, 1703, 497], [183, 516, 1702, 563], [183, 583, 1700, 631], [187, 650, 1701, 697], [184, 716, 1702, 765], [1800, 722, 1899, 931], [181, 782, 1701, 835], [183, 853, 1147, 903], [924, 917, 1630, 968], [1809, 1033, 1894, 1459], [726, 1058, 1162, 1134], [267, 1218, 1705, 1276], [182, 1290, 1491, 1341], [1333, 1359, 1631, 1405], [799, 1492, 1092, 1574], [272, 1660, 1704, 1707], [184, 1727, 1189, 1774], [1117, 1797, 1631, 1840], [264, 1912, 381, 1968], [264, 1977, 1703, 2026], [184, 2042, 1704, 2089], [181, 2103, 1706, 2152], [1826, 2147, 1878, 2224], [179, 2162, 1707, 2218], [181, 2228, 1706, 2278], [179, 2289, 1705, 2342], [181, 2354, 1581, 2404], [993, 2420, 1636, 2467]]}, "ocrImage": "https://pplines-online.bj.bcebos.com/deploy/official/paddleocr/structure-v3-online//dc44dbde-3d03-4382-b61c-a87811c0d9d9/overall_ocr_res_0.jpg?authorization=bce-auth-v1%2FALTAKDN8mY5KlNI7zaRpLmOqrw%2F2026-06-19T02%3A01%3A05Z%2F-1%2F%2F4663542c07658b9187f6a3d81d64221afb12cb8af1410d37d74918f876a0fc25", "inputImage": "https://pplines-online.bj.bcebos.com/deploy/official/paddleocr/structure-v3-online//dc44dbde-3d03-4382-b61c-a87811c0d9d9/input_img_0.jpg?authorization=bce-auth-v1%2FALTAKDN8mY5KlNI7zaRpLmOqrw%2F2026-06-19T02%3A01%3A04Z%2F-1%2F%2F47f937b8f60f9b2be8e4360923f97cb994c5592a9fd3c54f60be9f3feb5db938"}], "preprocessedImages": ["https://pplines-online.bj.bcebos.com/deploy/official/paddleocr/structure-v3-online//dc44dbde-3d03-4382-b61c-a87811c0d9d9/preprocessed_img_0.jpg?authorization=bce-auth-v1%2FALTAKDN8mY5KlNI7zaRpLmOqrw%2F2026-06-19T02%3A01%3A06Z%2F-1%2F%2Fd5da7c436833dad260730259c65f8644b9c95c5f3ccda48e6649dc26fac1d1ba"]}