{"layoutParsingResults": [{"prunedResult": {"page_count": null, "width": 2082, "height": 2915, "model_settings": {"use_doc_preprocessor": false, "use_seal_recognition": true, "use_table_recognition": true, "use_formula_recognition": true, "use_chart_recognition": false, "use_region_detection": true, "format_block_content": false, "markdown_ignore_labels": ["number", "footnote", "header", "header_image", "footer", "footer_image", "aside_text"]}, "parsing_res_list": [{"block_label": "text", "block_content": "有父兄之教子弟之学，竟以为秘诀相授受。而子若弟者，自其少有知识，已利禄熏于其心。幸而得之，则不识化民成俗尽职报国为何事；而不得者，则羡慕惭恨以终其身。于是其人才尽坏，而家风日替矣。岂不哀哉！\n", "block_bbox": [152, 257, 1721, 451], "block_id": 0, "block_order": 1}, {"block_label": "text", "block_content": "第25则。古之读书者，不言为文，盖道积厥躬，发为事业。现于威仪，词气皆文章也。自周之衰而文盛，文盛而著述大兴，于是秦汉一变也，魏晋六朝又一变也，唐宋元明又一变也，流为制义又一变也。今之习制义，则自童子至老壮无不为之。乡以此抡才，朝以此选俊，其孰能不为？然文，原无古今之殊，今试取前明及国朝诸大家之文，原本经术，旁该子史，体格神韵何尝有异于古？乃今无其学，而为其文者，又自创为卑弱软俗之语，而方高自衿许，以为吾将冠时流、取高第。稍知古文者，读之已不解为何义何法矣，岂不误后生而玷当世？吾尝欲选前人制义数百篇为家塾之式，而卒卒未遑。要之，学古人之读书，积久而流，则亦非世俗之所可及也。\n", "block_bbox": [151, 473, 1722, 1115], "block_id": 1, "block_order": 2}, {"block_label": "text", "block_content": "第26则。天生我而得为读书之人，幸矣；且予以尚能读书之资，又幸矣；无酬应之乱意，无饥寒之迫身，家世儒素、庭训禀承、师友之功具于门内，又大幸矣。及此时而不自力于学，老大无成，何待问哉？尝忆少时萧瑟之晨、寂寞之夜，心清致远，读书情景如在目前；其壮年以后，人事纷杂，都不省记。此盖真境故久而不忘，幻境故过而即灭也。若夫役役于妻子什宦，逐逐于饮食宴乐，言则不由衷之言，行则不自主之事，东奔西走，朝不辨朝，夕不知暮，老而回首，若竟未曾度此岁月，后人历数岁月，亦若并无此人。若此者，累累皆是也，悲夫！\n", "block_bbox": [151, 1137, 1723, 1701], "block_id": 2, "block_order": 3}, {"block_label": "text", "block_content": "第27则。今日视昨日，则昨日无有矣。明日视今日，则今日又无有矣。人生数十年，日月几何？少时玩弄流光，自缘后日方长；追迟暮观之，曾不能一瞬也。稍可不恨者，独曾读之书在耳。陶侃运甓，法大圣而惜荫，祖逖闻鸡，蹴凉朋而起舞，士诚念此，当有汲汲皇皇忘食与寝者矣。\n", "block_bbox": [151, 1725, 1726, 1996], "block_id": 3, "block_order": 4}, {"block_label": "text", "block_content": "第28则。读书先观其大意，次寻其条理，次味其意趣，正观之，反观之，侧观之，其内有所隐，其外有所包，必有四通八达、头头皆是者也。不善读书者，读此书只是此书；若善读书者，读一书而诸书咸在。朱字所云“默识心通、触处洞然”，正如此耳。制义以四子书命题，盖是六经之统会、百家之折衷，以一书通之，而经传子史皆其注脚矣。果能如此，则解经即是学文；而所为制义者，亦必精实磅礴，迥越流俗，非若彼浮游不根、旋荣旋落者之为识者所嗤也。", "block_bbox": [147, 2020, 1727, 2438], "block_id": 4, "block_order": 5}, {"block_label": "text", "block_content": "第29则。读经，要收纳到身心上来；读史，要推拓到事物上去。盛衰，治乱之由；兴废，存亡之迹。其己然者可考，则其未然者可知也。古人之用心行事，推见至隐，则《孟子》所云“知人论世”者也。至制作相承，则察其是非之", "block_bbox": [151, 2460, 1725, 2656], "block_id": 5, "block_order": 6}, {"block_label": "paragraph_title", "block_content": "渑池杜氏宗谱", "block_bbox": [1842, 772, 1926, 1520], "block_id": 6, "block_order": 7}, {"block_label": "text", "block_content": "三四八", "block_bbox": [1854, 2206, 1910, 2329], "block_id": 7, "block_order": 8}], "layout_det_res": {"boxes": [{"cls_id": 2, "label": "text", "score": 0.9383406639099121, "coordinate": [147.9381103515625, 2020.36376953125, 1727.487060546875, 2438.314453125]}, {"cls_id": 2, "label": "text", "score": 0.937568187713623, "coordinate": [151.22705078125, 1137.609375, 1723.5411376953125, 1701.03857421875]}, {"cls_id": 2, "label": "text", "score": 0.9370002150535583, "coordinate": [151.56878662109375, 1725.685546875, 1726.6494140625, 1996.224365234375]}, {"cls_id": 2, "label": "text", "score": 0.9323146939277649, "coordinate": [151.469970703125, 473.5735168457031, 1722.798095703125, 1115.3623046875]}, {"cls_id": 2, "label": "text", "score": 0.9177476167678833, "coordinate": [152.947265625, 257.1131591796875, 1721.086669921875, 451.63580322265625]}, {"cls_id": 2, "label": "text", "score": 0.9055455327033997, "coordinate": [151.26495361328125, 2460.808837890625, 1725.51513671875, 2656.793701171875]}, {"cls_id": 2, "label": "text", "score": 0.520972490310669, "coordinate": [1854.1044921875, 2206.4755859375, 1910.91162109375, 2329.86669921875]}, {"cls_id": 0, "label": "paragraph_title", "score": 0.3762691020965576, "coordinate": [1842.890380859375, 772.7706298828125, 1926.853759765625, 1520.3416748046875]}]}, "overall_ocr_res": {"model_settings": {"use_doc_preprocessor": false, "use_textline_orientation": true}, "dt_polys": [[[161, 257], [1719, 259], [1719, 307], [161, 305]], [[161, 330], [1719, 329], [1719, 379], [161, 380]], [[164, 404], [1252, 404], [1252, 451], [164, 451]], [[253, 476], [1719, 473], [1719, 525], [253, 527]], [[164, 552], [1718, 547], [1718, 597], [164, 602]], [[160, 623], [1721, 616], [1722, 673], [160, 680]], [[161, 696], [1723, 692], [1723, 749], [161, 753]], [[1829, 760], [1938, 760], [1938, 981], [1829, 981]], [[160, 771], [1719, 768], [1719, 822], [160, 825]], [[158, 843], [1720, 840], [1720, 897], [158, 900]], [[160, 919], [1718, 916], [1718, 970], [160, 973]], [[163, 994], [1717, 993], [1717, 1041], [163, 1042]], [[163, 1068], [729, 1068], [729, 1116], [163, 1116]], [[1844, 1088], [1932, 1088], [1930, 1523], [1842, 1522]], [[268, 1137], [1713, 1139], [1713, 1190], [268, 1188]], [[163, 1211], [1717, 1214], [1717, 1261], [163, 1258]], [[163, 1285], [1716, 1287], [1716, 1334], [163, 1332]], [[160, 1356], [1717, 1358], [1717, 1411], [160, 1409]], [[162, 1430], [1715, 1432], [1715, 1483], [162, 1481]], [[161, 1504], [1712, 1507], [1712, 1557], [161, 1554]], [[161, 1577], [1718, 1580], [1718, 1631], [161, 1628]], [[156, 1646], [243, 1646], [243, 1707], [156, 1707]], [[256, 1723], [1720, 1727], [1720, 1780], [256, 1776]], [[162, 1799], [1721, 1802], [1721, 1852], [162, 1849]], [[162, 1873], [1721, 1875], [1721, 1925], [162, 1923]], [[161, 1944], [1175, 1950], [1175, 2001], [161, 1995]], [[258, 2021], [1716, 2024], [1716, 2072], [258, 2069]], [[162, 2094], [1722, 2095], [1722, 2146], [162, 2145]], [[161, 2168], [1720, 2168], [1720, 2218], [161, 2218]], [[1849, 2201], [1914, 2200], [1916, 2336], [1852, 2337]], [[159, 2240], [1723, 2240], [1723, 2293], [159, 2293]], [[160, 2313], [1721, 2313], [1721, 2367], [160, 2367]], [[159, 2387], [1697, 2387], [1697, 2441], [159, 2441]], [[252, 2459], [1722, 2459], [1722, 2513], [252, 2513]], [[160, 2534], [1720, 2533], [1720, 2584], [160, 2585]], [[160, 2606], [1721, 2606], [1721, 2660], [160, 2660]]], "text_det_params": {"limit_side_len": 736, "limit_type": "min", "thresh": 0.3, "max_side_limit": 4000, "box_thresh": 0.6, "unclip_ratio": 1.5}, "text_type": "general", "textline_orientation_angles": [0, 0, 0, 0, 0, 0, 0, 0, 0, 0, 0, 0, 0, 0, 0, 0, 0, 0, 0, 0, 0, 0, 0, 0, 0, 0, 0, 0, 0, 0, 0, 0, 0, 0, 0, 0], "text_rec_score_thresh": 0.0, "return_word_box": false, "rec_texts": ["有父兄之教子弟之学，竟以为秘诀相授受。而子若弟者，自其少有知识，已利禄", "熏于其心。幸而得之，则不识化民成俗尽职报国为何事；而不得者，则羡慕惭恨", "以终其身。于是其人才尽坏，而家风日替矣。岂不哀哉！", "第25则。古之读书者，不言为文，盖道积厥躬，发为事业。现于威仪，词", "气皆文章也。自周之衰而文盛，文盛而著述大兴，于是秦汉一变也，魏晋六朝又", "一变也，唐宋元明又一变也，流为制义又一变也。今之习制义，则自童子至老壮", "无不为之。乡以此抡才，朝以此选俊，其孰能不为？然文，原无古今之殊，今试", "渑池", "取前明及国朝诸大家之文，原本经术，旁该子史，体格神韵何尝有异于古？乃今", "无其学，而为其文者，又自创为卑弱软俗之语，而方高自衿许，以为吾将冠时", "流、取高第。稍知古文者，读之已不解为何义何法矣，岂不误后生而玷当世？吾", "尝欲选前人制义数百篇为家塾之式，而卒卒未遑。要之，学古人之读书，积久而", "流，则亦非世俗之所可及也。", "杜氏宗谱", "第26则。天生我而得为读书之人，幸矣；且予以尚能读书之资，又幸矣；", "无酬应之乱意，无饥寒之迫身，家世儒素、庭训禀承、师友之功具于门内，又大", "幸矣。及此时而不自力于学，老大无成，何待问哉？尝忆少时萧瑟之晨、寂寞之", "夜，心清致远，读书情景如在目前；其壮年以后，人事纷杂，都不省记。此盖真", "境故久而不忘，幻境故过而即灭也。若夫役役于妻子什宦，逐逐于饮食宴乐，言", "则不由衷之言，行则不自主之事，东奔西走，朝不辨朝，夕不知暮，老而回首，", "若竟未曾度此岁月，后人历数岁月，亦若并无此人。若此者，累累皆是也，悲", "夫！", "第27则。今日视昨日，则昨日无有矣。明日视今日，则今日又无有矣。人", "生数十年，日月几何？少时玩弄流光，自缘后日方长；追迟暮观之，曾不能一瞬", "也。稍可不恨者，独曾读之书在耳。陶侃运甓，法大圣而惜荫，祖逖闻鸡，蹴凉", "朋而起舞，士诚念此，当有汲汲皇皇忘食与寝者矣。", "第28则。读书先观其大意，次寻其条理，次味其意趣，正观之，反观之，", "侧观之，其内有所隐，其外有所包，必有四通八达、头头皆是者也。不善读书", "者，读此书只是此书；若善读书者，读一书而诸书咸在。朱字所云“默识心通、", "三四八", "触处洞然”，正如此耳。制义以四子书命题，盖是六经之统会、百家之折衷，以", "一书通之，而经传子史皆其注脚矣。果能如此，则解经即是学文；而所为制义", "者，亦必精实磅礴，迥越流俗，非若彼浮游不根、旋荣旋落者之为识者所嗤也。", "第29则。读经，要收纳到身心上来；读史，要推拓到事物上去。盛衰，治", "乱之由；兴废，存亡之迹。其己然者可考，则其未然者可知也。古人之用心行", "事，推见至隐，则《孟子》所云“知人论世”者也。至制作相承，则察其是非之"], "rec_scores": [0.9951812624931335, 0.9970006942749023, 0.996056079864502, 0.9964533448219299, 0.9964828491210938, 0.9955300688743591, 0.9748899340629578, 0.9390259385108948, 0.9945126175880432, 0.9936577081680298, 0.9944872260093689, 0.9803963899612427, 0.9991577863693237, 0.9935302734375, 0.9943556189537048, 0.9943917393684387, 0.9914679527282715, 0.9977229237556458, 0.9975325465202332, 0.9962983131408691, 0.9976009130477905, 0.9814656972885132, 0.9976181387901306, 0.977601170539856, 0.9942383766174316, 0.9953782558441162, 0.9971702098846436, 0.9973868131637573, 0.9875021576881409, 0.9987857937812805, 0.9933640360832214, 0.9963502287864685, 0.9922403693199158, 0.9968864917755127, 0.9940308928489685, 0.9913657903671265], "rec_polys": [[[161, 257], [1719, 259], [1719, 307], [161, 305]], [[161, 330], [1719, 329], [1719, 379], [161, 380]], [[164, 404], [1252, 404], [1252, 451], [164, 451]], [[253, 476], [1719, 473], [1719, 525], [253, 527]], [[164, 552], [1718, 547], [1718, 597], [164, 602]], [[160, 623], [1721, 616], [1722, 673], [160, 680]], [[161, 696], [1723, 692], [1723, 749], [161, 753]], [[1829, 760], [1938, 760], [1938, 981], [1829, 981]], [[160, 771], [1719, 768], [1719, 822], [160, 825]], [[158, 843], [1720, 840], [1720, 897], [158, 900]], [[160, 919], [1718, 916], [1718, 970], [160, 973]], [[163, 994], [1717, 993], [1717, 1041], [163, 1042]], [[163, 1068], [729, 1068], [729, 1116], [163, 1116]], [[1844, 1088], [1932, 1088], [1930, 1523], [1842, 1522]], [[268, 1137], [1713, 1139], [1713, 1190], [268, 1188]], [[163, 1211], [1717, 1214], [1717, 1261], [163, 1258]], [[163, 1285], [1716, 1287], [1716, 1334], [163, 1332]], [[160, 1356], [1717, 1358], [1717, 1411], [160, 1409]], [[162, 1430], [1715, 1432], [1715, 1483], [162, 1481]], [[161, 1504], [1712, 1507], [1712, 1557], [161, 1554]], [[161, 1577], [1718, 1580], [1718, 1631], [161, 1628]], [[156, 1646], [243, 1646], [243, 1707], [156, 1707]], [[256, 1723], [1720, 1727], [1720, 1780], [256, 1776]], [[162, 1799], [1721, 1802], [1721, 1852], [162, 1849]], [[162, 1873], [1721, 1875], [1721, 1925], [162, 1923]], [[161, 1944], [1175, 1950], [1175, 2001], [161, 1995]], [[258, 2021], [1716, 2024], [1716, 2072], [258, 2069]], [[162, 2094], [1722, 2095], [1722, 2146], [162, 2145]], [[161, 2168], [1720, 2168], [1720, 2218], [161, 2218]], [[1849, 2201], [1914, 2200], [1916, 2336], [1852, 2337]], [[159, 2240], [1723, 2240], [1723, 2293], [159, 2293]], [[160, 2313], [1721, 2313], [1721, 2367], [160, 2367]], [[159, 2387], [1697, 2387], [1697, 2441], [159, 2441]], [[252, 2459], [1722, 2459], [1722, 2513], [252, 2513]], [[160, 2534], [1720, 2533], [1720, 2584], [160, 2585]], [[160, 2606], [1721, 2606], [1721, 2660], [160, 2660]]], "rec_boxes": [[161, 257, 1719, 307], [161, 329, 1719, 380], [164, 404, 1252, 451], [253, 473, 1719, 527], [164, 547, 1718, 602], [160, 616, 1722, 680], [161, 692, 1723, 753], [1829, 760, 1938, 981], [160, 768, 1719, 825], [158, 840, 1720, 900], [160, 916, 1718, 973], [163, 993, 1717, 1042], [163, 1068, 729, 1116], [1842, 1088, 1932, 1523], [268, 1137, 1713, 1190], [163, 1211, 1717, 1261], [163, 1285, 1716, 1334], [160, 1356, 1717, 1411], [162, 1430, 1715, 1483], [161, 1504, 1712, 1557], [161, 1577, 1718, 1631], [156, 1646, 243, 1707], [256, 1723, 1720, 1780], [162, 1799, 1721, 1852], [162, 1873, 1721, 1925], [161, 1944, 1175, 2001], [258, 2021, 1716, 2072], [162, 2094, 1722, 2146], [161, 2168, 1720, 2218], [1849, 2200, 1916, 2337], [159, 2240, 1723, 2293], [160, 2313, 1721, 2367], [159, 2387, 1697, 2441], [252, 2459, 1722, 2513], [160, 2533, 1720, 2585], [160, 2606, 1721, 2660]]}}, "markdown": {"text": "有父兄之教子弟之学，竟以为秘诀相授受。而子若弟者，自其少有知识，已利禄熏于其心。幸而得之，则不识化民成俗尽职报国为何事；而不得者，则羡慕惭恨以终其身。于是其人才尽坏，而家风日替矣。岂不哀哉！\n\n\n\n第25则。古之读书者，不言为文，盖道积厥躬，发为事业。现于威仪，词气皆文章也。自周之衰而文盛，文盛而著述大兴，于是秦汉一变也，魏晋六朝又一变也，唐宋元明又一变也，流为制义又一变也。今之习制义，则自童子至老壮无不为之。乡以此抡才，朝以此选俊，其孰能不为？然文，原无古今之殊，今试取前明及国朝诸大家之文，原本经术，旁该子史，体格神韵何尝有异于古？乃今无其学，而为其文者，又自创为卑弱软俗之语，而方高自衿许，以为吾将冠时流、取高第。稍知古文者，读之已不解为何义何法矣，岂不误后生而玷当世？吾尝欲选前人制义数百篇为家塾之式，而卒卒未遑。要之，学古人之读书，积久而流，则亦非世俗之所可及也。\n\n\n\n第26则。天生我而得为读书之人，幸矣；且予以尚能读书之资，又幸矣；无酬应之乱意，无饥寒之迫身，家世儒素、庭训禀承、师友之功具于门内，又大幸矣。及此时而不自力于学，老大无成，何待问哉？尝忆少时萧瑟之晨、寂寞之夜，心清致远，读书情景如在目前；其壮年以后，人事纷杂，都不省记。此盖真境故久而不忘，幻境故过而即灭也。若夫役役于妻子什宦，逐逐于饮食宴乐，言则不由衷之言，行则不自主之事，东奔西走，朝不辨朝，夕不知暮，老而回首，若竟未曾度此岁月，后人历数岁月，亦若并无此人。若此者，累累皆是也，悲夫！\n\n\n\n第27则。今日视昨日，则昨日无有矣。明日视今日，则今日又无有矣。人生数十年，日月几何？少时玩弄流光，自缘后日方长；追迟暮观之，曾不能一瞬也。稍可不恨者，独曾读之书在耳。陶侃运甓，法大圣而惜荫，祖逖闻鸡，蹴凉朋而起舞，士诚念此，当有汲汲皇皇忘食与寝者矣。\n\n\n\n第28则。读书先观其大意，次寻其条理，次味其意趣，正观之，反观之，侧观之，其内有所隐，其外有所包，必有四通八达、头头皆是者也。不善读书者，读此书只是此书；若善读书者，读一书而诸书咸在。朱字所云“默识心通、触处洞然”，正如此耳。制义以四子书命题，盖是六经之统会、百家之折衷，以一书通之，而经传子史皆其注脚矣。果能如此，则解经即是学文；而所为制义者，亦必精实磅礴，迥越流俗，非若彼浮游不根、旋荣旋落者之为识者所嗤也。\n\n第29则。读经，要收纳到身心上来；读史，要推拓到事物上去。盛衰，治乱之由；兴废，存亡之迹。其己然者可考，则其未然者可知也。古人之用心行事，推见至隐，则《孟子》所云“知人论世”者也。至制作相承，则察其是非之\n\n## 渑池杜氏宗谱\n\n三四八", "isStart": false, "isEnd": true, "images": {}}, "outputImages": {"layout_det_res": "https://pplines-online.bj.bcebos.com/deploy/official/paddleocr/structure-v3-online//11f9d21b-3f84-478c-bf5e-d5199850fe46/layout_det_res_0.jpg?authorization=bce-auth-v1%2FALTAKDN8mY5KlNI7zaRpLmOqrw%2F2026-06-19T02%3A29%3A37Z%2F-1%2F%2F4bdfb1483ac36e9cffeda08e62b9b844e32f19d945b8dc5dc071ca0cb7c1d4a6", "region_det_res": "https://pplines-online.bj.bcebos.com/deploy/official/paddleocr/structure-v3-online//11f9d21b-3f84-478c-bf5e-d5199850fe46/region_det_res_0.jpg?authorization=bce-auth-v1%2FALTAKDN8mY5KlNI7zaRpLmOqrw%2F2026-06-19T02%3A29%3A38Z%2F-1%2F%2Fc92ad2c6eeda581963e034519a9f6a0571cb3c8d7eed5ee50df3f2edee5e1344", "overall_ocr_res": "https://pplines-online.bj.bcebos.com/deploy/official/paddleocr/structure-v3-online//11f9d21b-3f84-478c-bf5e-d5199850fe46/overall_ocr_res_0.jpg?authorization=bce-auth-v1%2FALTAKDN8mY5KlNI7zaRpLmOqrw%2F2026-06-19T02%3A29%3A38Z%2F-1%2F%2F6afc43be080773c20de8dd1d41e978ccbff4517c1a6d0193e0269e60a9910f60", "layout_order_res": "https://pplines-online.bj.bcebos.com/deploy/official/paddleocr/structure-v3-online//11f9d21b-3f84-478c-bf5e-d5199850fe46/layout_order_res_0.jpg?authorization=bce-auth-v1%2FALTAKDN8mY5KlNI7zaRpLmOqrw%2F2026-06-19T02%3A29%3A38Z%2F-1%2F%2Fc98c01c8b9e3a6f39c4fb59101b64b8dee472714209c0a30eccfaa8a7d73d819"}, "inputImage": "https://pplines-online.bj.bcebos.com/deploy/official/paddleocr/structure-v3-online//11f9d21b-3f84-478c-bf5e-d5199850fe46/input_img_0.jpg?authorization=bce-auth-v1%2FALTAKDN8mY5KlNI7zaRpLmOqrw%2F2026-06-19T02%3A29%3A37Z%2F-1%2F%2F72e0f2043404ba0a614ce9f9d71b81272864108eb65f3fcc6b6673727876b54c"}], "dataInfo": {"width": 2082, "height": 2915, "type": "image"}, "ocrResults": [{"prunedResult": {"model_settings": {"use_doc_preprocessor": false, "use_textline_orientation": true}, "dt_polys": [[[161, 257], [1719, 259], [1719, 307], [161, 305]], [[161, 330], [1719, 329], [1719, 379], [161, 380]], [[164, 404], [1252, 404], [1252, 451], [164, 451]], [[253, 476], [1719, 473], [1719, 525], [253, 527]], [[164, 552], [1718, 547], [1718, 597], [164, 602]], [[160, 623], [1721, 616], [1722, 673], [160, 680]], [[161, 696], [1723, 692], [1723, 749], [161, 753]], [[1829, 760], [1938, 760], [1938, 981], [1829, 981]], [[160, 771], [1719, 768], [1719, 822], [160, 825]], [[158, 843], [1720, 840], [1720, 897], [158, 900]], [[160, 919], [1718, 916], [1718, 970], [160, 973]], [[163, 994], [1717, 993], [1717, 1041], [163, 1042]], [[163, 1068], [729, 1068], [729, 1116], [163, 1116]], [[1844, 1088], [1932, 1088], [1930, 1523], [1842, 1522]], [[268, 1137], [1713, 1139], [1713, 1190], [268, 1188]], [[163, 1211], [1717, 1214], [1717, 1261], [163, 1258]], [[163, 1285], [1716, 1287], [1716, 1334], [163, 1332]], [[160, 1356], [1717, 1358], [1717, 1411], [160, 1409]], [[162, 1430], [1715, 1432], [1715, 1483], [162, 1481]], [[161, 1504], [1712, 1507], [1712, 1557], [161, 1554]], [[161, 1577], [1718, 1580], [1718, 1631], [161, 1628]], [[156, 1646], [243, 1646], [243, 1707], [156, 1707]], [[256, 1723], [1720, 1727], [1720, 1780], [256, 1776]], [[162, 1799], [1721, 1802], [1721, 1852], [162, 1849]], [[162, 1873], [1721, 1875], [1721, 1925], [162, 1923]], [[161, 1944], [1175, 1950], [1175, 2001], [161, 1995]], [[258, 2021], [1716, 2024], [1716, 2072], [258, 2069]], [[162, 2094], [1722, 2095], [1722, 2146], [162, 2145]], [[161, 2168], [1720, 2168], [1720, 2218], [161, 2218]], [[1849, 2201], [1914, 2200], [1916, 2336], [1852, 2337]], [[159, 2240], [1723, 2240], [1723, 2293], [159, 2293]], [[160, 2313], [1721, 2313], [1721, 2367], [160, 2367]], [[159, 2387], [1697, 2387], [1697, 2441], [159, 2441]], [[252, 2459], [1722, 2459], [1722, 2513], [252, 2513]], [[160, 2534], [1720, 2533], [1720, 2584], [160, 2585]], [[160, 2606], [1721, 2606], [1721, 2660], [160, 2660]]], "text_det_params": {"limit_side_len": 736, "limit_type": "min", "thresh": 0.3, "max_side_limit": 4000, "box_thresh": 0.6, "unclip_ratio": 1.5}, "text_type": "general", "textline_orientation_angles": [0, 0, 0, 0, 0, 0, 0, 0, 0, 0, 0, 0, 0, 0, 0, 0, 0, 0, 0, 0, 0, 0, 0, 0, 0, 0, 0, 0, 0, 0, 0, 0, 0, 0, 0, 0], "text_rec_score_thresh": 0.0, "return_word_box": false, "rec_texts": ["有父兄之教子弟之学，竟以为秘诀相授受。而子若弟者，自其少有知识，已利禄", "熏于其心。幸而得之，则不识化民成俗尽职报国为何事；而不得者，则羡慕惭恨", "以终其身。于是其人才尽坏，而家风日替矣。岂不哀哉！", "第25则。古之读书者，不言为文，盖道积厥躬，发为事业。现于威仪，词", "气皆文章也。自周之衰而文盛，文盛而著述大兴，于是秦汉一变也，魏晋六朝又", "一变也，唐宋元明又一变也，流为制义又一变也。今之习制义，则自童子至老壮", "无不为之。乡以此抡才，朝以此选俊，其孰能不为？然文，原无古今之殊，今试", "渑池", "取前明及国朝诸大家之文，原本经术，旁该子史，体格神韵何尝有异于古？乃今", "无其学，而为其文者，又自创为卑弱软俗之语，而方高自衿许，以为吾将冠时", "流、取高第。稍知古文者，读之已不解为何义何法矣，岂不误后生而玷当世？吾", "尝欲选前人制义数百篇为家塾之式，而卒卒未遑。要之，学古人之读书，积久而", "流，则亦非世俗之所可及也。", "杜氏宗谱", "第26则。天生我而得为读书之人，幸矣；且予以尚能读书之资，又幸矣；", "无酬应之乱意，无饥寒之迫身，家世儒素、庭训禀承、师友之功具于门内，又大", "幸矣。及此时而不自力于学，老大无成，何待问哉？尝忆少时萧瑟之晨、寂寞之", "夜，心清致远，读书情景如在目前；其壮年以后，人事纷杂，都不省记。此盖真", "境故久而不忘，幻境故过而即灭也。若夫役役于妻子什宦，逐逐于饮食宴乐，言", "则不由衷之言，行则不自主之事，东奔西走，朝不辨朝，夕不知暮，老而回首，", "若竟未曾度此岁月，后人历数岁月，亦若并无此人。若此者，累累皆是也，悲", "夫！", "第27则。今日视昨日，则昨日无有矣。明日视今日，则今日又无有矣。人", "生数十年，日月几何？少时玩弄流光，自缘后日方长；追迟暮观之，曾不能一瞬", "也。稍可不恨者，独曾读之书在耳。陶侃运甓，法大圣而惜荫，祖逖闻鸡，蹴凉", "朋而起舞，士诚念此，当有汲汲皇皇忘食与寝者矣。", "第28则。读书先观其大意，次寻其条理，次味其意趣，正观之，反观之，", "侧观之，其内有所隐，其外有所包，必有四通八达、头头皆是者也。不善读书", "者，读此书只是此书；若善读书者，读一书而诸书咸在。朱字所云“默识心通、", "三四八", "触处洞然”，正如此耳。制义以四子书命题，盖是六经之统会、百家之折衷，以", "一书通之，而经传子史皆其注脚矣。果能如此，则解经即是学文；而所为制义", "者，亦必精实磅礴，迥越流俗，非若彼浮游不根、旋荣旋落者之为识者所嗤也。", "第29则。读经，要收纳到身心上来；读史，要推拓到事物上去。盛衰，治", "乱之由；兴废，存亡之迹。其己然者可考，则其未然者可知也。古人之用心行", "事，推见至隐，则《孟子》所云“知人论世”者也。至制作相承，则察其是非之"], "rec_scores": [0.9951812624931335, 0.9970006942749023, 0.996056079864502, 0.9964533448219299, 0.9964828491210938, 0.9955300688743591, 0.9748899340629578, 0.9390259385108948, 0.9945126175880432, 0.9936577081680298, 0.9944872260093689, 0.9803963899612427, 0.9991577863693237, 0.9935302734375, 0.9943556189537048, 0.9943917393684387, 0.9914679527282715, 0.9977229237556458, 0.9975325465202332, 0.9962983131408691, 0.9976009130477905, 0.9814656972885132, 0.9976181387901306, 0.977601170539856, 0.9942383766174316, 0.9953782558441162, 0.9971702098846436, 0.9973868131637573, 0.9875021576881409, 0.9987857937812805, 0.9933640360832214, 0.9963502287864685, 0.9922403693199158, 0.9968864917755127, 0.9940308928489685, 0.9913657903671265], "rec_polys": [[[161, 257], [1719, 259], [1719, 307], [161, 305]], [[161, 330], [1719, 329], [1719, 379], [161, 380]], [[164, 404], [1252, 404], [1252, 451], [164, 451]], [[253, 476], [1719, 473], [1719, 525], [253, 527]], [[164, 552], [1718, 547], [1718, 597], [164, 602]], [[160, 623], [1721, 616], [1722, 673], [160, 680]], [[161, 696], [1723, 692], [1723, 749], [161, 753]], [[1829, 760], [1938, 760], [1938, 981], [1829, 981]], [[160, 771], [1719, 768], [1719, 822], [160, 825]], [[158, 843], [1720, 840], [1720, 897], [158, 900]], [[160, 919], [1718, 916], [1718, 970], [160, 973]], [[163, 994], [1717, 993], [1717, 1041], [163, 1042]], [[163, 1068], [729, 1068], [729, 1116], [163, 1116]], [[1844, 1088], [1932, 1088], [1930, 1523], [1842, 1522]], [[268, 1137], [1713, 1139], [1713, 1190], [268, 1188]], [[163, 1211], [1717, 1214], [1717, 1261], [163, 1258]], [[163, 1285], [1716, 1287], [1716, 1334], [163, 1332]], [[160, 1356], [1717, 1358], [1717, 1411], [160, 1409]], [[162, 1430], [1715, 1432], [1715, 1483], [162, 1481]], [[161, 1504], [1712, 1507], [1712, 1557], [161, 1554]], [[161, 1577], [1718, 1580], [1718, 1631], [161, 1628]], [[156, 1646], [243, 1646], [243, 1707], [156, 1707]], [[256, 1723], [1720, 1727], [1720, 1780], [256, 1776]], [[162, 1799], [1721, 1802], [1721, 1852], [162, 1849]], [[162, 1873], [1721, 1875], [1721, 1925], [162, 1923]], [[161, 1944], [1175, 1950], [1175, 2001], [161, 1995]], [[258, 2021], [1716, 2024], [1716, 2072], [258, 2069]], [[162, 2094], [1722, 2095], [1722, 2146], [162, 2145]], [[161, 2168], [1720, 2168], [1720, 2218], [161, 2218]], [[1849, 2201], [1914, 2200], [1916, 2336], [1852, 2337]], [[159, 2240], [1723, 2240], [1723, 2293], [159, 2293]], [[160, 2313], [1721, 2313], [1721, 2367], [160, 2367]], [[159, 2387], [1697, 2387], [1697, 2441], [159, 2441]], [[252, 2459], [1722, 2459], [1722, 2513], [252, 2513]], [[160, 2534], [1720, 2533], [1720, 2584], [160, 2585]], [[160, 2606], [1721, 2606], [1721, 2660], [160, 2660]]], "rec_boxes": [[161, 257, 1719, 307], [161, 329, 1719, 380], [164, 404, 1252, 451], [253, 473, 1719, 527], [164, 547, 1718, 602], [160, 616, 1722, 680], [161, 692, 1723, 753], [1829, 760, 1938, 981], [160, 768, 1719, 825], [158, 840, 1720, 900], [160, 916, 1718, 973], [163, 993, 1717, 1042], [163, 1068, 729, 1116], [1842, 1088, 1932, 1523], [268, 1137, 1713, 1190], [163, 1211, 1717, 1261], [163, 1285, 1716, 1334], [160, 1356, 1717, 1411], [162, 1430, 1715, 1483], [161, 1504, 1712, 1557], [161, 1577, 1718, 1631], [156, 1646, 243, 1707], [256, 1723, 1720, 1780], [162, 1799, 1721, 1852], [162, 1873, 1721, 1925], [161, 1944, 1175, 2001], [258, 2021, 1716, 2072], [162, 2094, 1722, 2146], [161, 2168, 1720, 2218], [1849, 2200, 1916, 2337], [159, 2240, 1723, 2293], [160, 2313, 1721, 2367], [159, 2387, 1697, 2441], [252, 2459, 1722, 2513], [160, 2533, 1720, 2585], [160, 2606, 1721, 2660]]}, "ocrImage": "https://pplines-online.bj.bcebos.com/deploy/official/paddleocr/structure-v3-online//11f9d21b-3f84-478c-bf5e-d5199850fe46/overall_ocr_res_0.jpg?authorization=bce-auth-v1%2FALTAKDN8mY5KlNI7zaRpLmOqrw%2F2026-06-19T02%3A29%3A38Z%2F-1%2F%2F6afc43be080773c20de8dd1d41e978ccbff4517c1a6d0193e0269e60a9910f60", "inputImage": "https://pplines-online.bj.bcebos.com/deploy/official/paddleocr/structure-v3-online//11f9d21b-3f84-478c-bf5e-d5199850fe46/input_img_0.jpg?authorization=bce-auth-v1%2FALTAKDN8mY5KlNI7zaRpLmOqrw%2F2026-06-19T02%3A29%3A37Z%2F-1%2F%2F72e0f2043404ba0a614ce9f9d71b81272864108eb65f3fcc6b6673727876b54c"}], "preprocessedImages": ["https://pplines-online.bj.bcebos.com/deploy/official/paddleocr/structure-v3-online//11f9d21b-3f84-478c-bf5e-d5199850fe46/preprocessed_img_0.jpg?authorization=bce-auth-v1%2FALTAKDN8mY5KlNI7zaRpLmOqrw%2F2026-06-19T02%3A29%3A39Z%2F-1%2F%2Ff2579f20e82ee863adec42d39dd85a9ed44ec361edf114c9718ed4fae6180e3e"]}