{"layoutParsingResults": [{"prunedResult": {"page_count": null, "width": 1931, "height": 2588, "model_settings": {"use_doc_preprocessor": false, "use_seal_recognition": true, "use_table_recognition": true, "use_formula_recognition": true, "use_chart_recognition": false, "use_region_detection": true, "format_block_content": false, "markdown_ignore_labels": ["number", "footnote", "header", "header_image", "footer", "footer_image", "aside_text"]}, "parsing_res_list": [{"block_label": "paragraph_title", "block_content": "下营村", "block_bbox": [894, 223, 1173, 285], "block_id": 0, "block_order": 1}, {"block_label": "text", "block_content": "下营村，为洛宁县（旧名永宁县）河底镇的一个建制村，旧名营里村，国营二七五处所在地。\n", "block_bbox": [319, 352, 1747, 461], "block_id": 1, "block_order": 2}, {"block_label": "text", "block_content": "流芳公后裔由渑池坻坞先迁永宁县城。数世后，世科、世登两兄弟迁下营村，世登子六（前五子世系未详），其第六子国敬，有子四：长居宜阳县韩城镇东官庄，次居杨坡、西官庄，四居杜家阙，三仍居下营。十五世前据朝宦墓碑补。", "block_bbox": [318, 478, 1747, 653], "block_id": 2, "block_order": 3}, {"block_label": "paragraph_title", "block_content": "渑池杜氏宗谱", "block_bbox": [154, 683, 232, 1349], "block_id": 3, "block_order": 4}, {"block_label": "text", "block_content": "其世系为：", "block_bbox": [391, 673, 577, 718], "block_id": 4, "block_order": 5}, {"block_label": "text", "block_content": "流芳公—失传—失传—失传—失传—失传—世科", "block_bbox": [391, 734, 1235, 782], "block_id": 5, "block_order": 6}, {"block_label": "text", "block_content": "世登一国敬一朝宦", "block_bbox": [1151, 794, 1478, 840], "block_id": 6, "block_order": 7}, {"block_label": "text", "block_content": "二三九", "block_bbox": [173, 1945, 223, 2058], "block_id": 7, "block_order": 8}], "layout_det_res": {"boxes": [{"cls_id": 2, "label": "text", "score": 0.9266501665115356, "coordinate": [318.88946533203125, 478.4002685546875, 1747.203857421875, 653.7447509765625]}, {"cls_id": 2, "label": "text", "score": 0.8775710463523865, "coordinate": [319.994140625, 352.4544677734375, 1747.29541015625, 461.680908203125]}, {"cls_id": 0, "label": "paragraph_title", "score": 0.8203232884407043, "coordinate": [894.8824462890625, 223.5638427734375, 1173.1422119140625, 285.0732421875]}, {"cls_id": 2, "label": "text", "score": 0.7181994915008545, "coordinate": [391.261474609375, 673.4840087890625, 577.4822998046875, 718.2252197265625]}, {"cls_id": 2, "label": "text", "score": 0.6721271276473999, "coordinate": [391.7127685546875, 734.1400146484375, 1235.4984130859375, 782.3226318359375]}, {"cls_id": 2, "label": "text", "score": 0.6337605714797974, "coordinate": [1151.55517578125, 794.5250244140625, 1478.12890625, 840.6099853515625]}, {"cls_id": 2, "label": "text", "score": 0.5670062303543091, "coordinate": [173.89974975585938, 1945.72412109375, 223.80624389648438, 2058.764404296875]}, {"cls_id": 0, "label": "paragraph_title", "score": 0.3806113600730896, "coordinate": [154.8472900390625, 683.310791015625, 232.1441650390625, 1349.6787109375]}]}, "overall_ocr_res": {"model_settings": {"use_doc_preprocessor": false, "use_textline_orientation": true}, "dt_polys": [[[898, 222], [1176, 222], [1176, 292], [898, 292]], [[408, 352], [1744, 355], [1744, 399], [408, 396]], [[326, 417], [551, 417], [551, 465], [326, 465]], [[407, 482], [1745, 479], [1745, 523], [407, 526]], [[327, 547], [1745, 541], [1745, 585], [327, 591]], [[328, 612], [1436, 608], [1436, 652], [328, 656]], [[144, 678], [238, 678], [238, 873], [144, 873]], [[393, 673], [577, 673], [577, 722], [393, 722]], [[397, 739], [1230, 735], [1230, 779], [397, 783]], [[1152, 799], [1478, 795], [1479, 840], [1153, 844]], [[153, 960], [234, 959], [236, 1351], [155, 1351]], [[169, 1943], [229, 1943], [229, 2064], [169, 2064]]], "text_det_params": {"limit_side_len": 736, "limit_type": "min", "thresh": 0.3, "max_side_limit": 4000, "box_thresh": 0.6, "unclip_ratio": 1.5}, "text_type": "general", "textline_orientation_angles": [0, 0, 0, 0, 0, 0, 0, 0, 0, 0, 0, 0], "text_rec_score_thresh": 0.0, "return_word_box": false, "rec_texts": ["下营村", "下营村，为洛宁县（旧名永宁县）河底镇的一个建制村，旧名营里村，国营二七", "五处所在地。", "流芳公后裔由渑池坻坞先迁永宁县城。数世后，世科、世登两兄弟迁下营村，世", "登子六（前五子世系未详），其第六子国敬，有子四：长居宜阳县韩城镇东官庄，次居", "杨坡、西官庄，四居杜家阙，三仍居下营。十五世前据朝宦墓碑补。", "渑池", "其世系为：", "流芳公—失传—失传—失传—失传—失传—世科", "世登一国敬一朝宦", "杜氏宗谱", "二三九"], "rec_scores": [0.9987604022026062, 0.9895967841148376, 0.9994428157806396, 0.9756117463111877, 0.9861790537834167, 0.9864251017570496, 0.8682790994644165, 0.9966435432434082, 0.9176371693611145, 0.8924490213394165, 0.9909384250640869, 0.9895793795585632], "rec_polys": [[[898, 222], [1176, 222], [1176, 292], [898, 292]], [[408, 352], [1744, 355], [1744, 399], [408, 396]], [[326, 417], [551, 417], [551, 465], [326, 465]], [[407, 482], [1745, 479], [1745, 523], [407, 526]], [[327, 547], [1745, 541], [1745, 585], [327, 591]], [[328, 612], [1436, 608], [1436, 652], [328, 656]], [[144, 678], [238, 678], [238, 873], [144, 873]], [[393, 673], [577, 673], [577, 722], [393, 722]], [[397, 739], [1230, 735], [1230, 779], [397, 783]], [[1152, 799], [1478, 795], [1479, 840], [1153, 844]], [[153, 960], [234, 959], [236, 1351], [155, 1351]], [[169, 1943], [229, 1943], [229, 2064], [169, 2064]]], "rec_boxes": [[898, 222, 1176, 292], [408, 352, 1744, 399], [326, 417, 551, 465], [407, 479, 1745, 526], [327, 541, 1745, 591], [328, 608, 1436, 656], [144, 678, 238, 873], [393, 673, 577, 722], [397, 735, 1230, 783], [1152, 795, 1479, 844], [153, 959, 236, 1351], [169, 1943, 229, 2064]]}}, "markdown": {"text": "## 下营村\n\n下营村，为洛宁县（旧名永宁县）河底镇的一个建制村，旧名营里村，国营二七五处所在地。\n\n\n\n流芳公后裔由渑池坻坞先迁永宁县城。数世后，世科、世登两兄弟迁下营村，世登子六（前五子世系未详），其第六子国敬，有子四：长居宜阳县韩城镇东官庄，次居杨坡、西官庄，四居杜家阙，三仍居下营。十五世前据朝宦墓碑补。\n\n## 渑池杜氏宗谱\n\n其世系为：\n\n流芳公—失传—失传—失传—失传—失传—世科\n\n世登一国敬一朝宦\n\n二三九", "isStart": false, "isEnd": true, "images": {}}, "outputImages": {"layout_det_res": "https://pplines-online.bj.bcebos.com/deploy/official/paddleocr/structure-v3-online//925a28c2-7226-47d3-a892-082bea01033b/layout_det_res_0.jpg?authorization=bce-auth-v1%2FALTAKDN8mY5KlNI7zaRpLmOqrw%2F2026-06-19T02%3A18%3A26Z%2F-1%2F%2F3b438ba547031a07e6199c7dffaf7cbf5ccf2d2ad4ddb6f0cf99a082d59dbac5", "region_det_res": "https://pplines-online.bj.bcebos.com/deploy/official/paddleocr/structure-v3-online//925a28c2-7226-47d3-a892-082bea01033b/region_det_res_0.jpg?authorization=bce-auth-v1%2FALTAKDN8mY5KlNI7zaRpLmOqrw%2F2026-06-19T02%3A18%3A26Z%2F-1%2F%2F85abed2103078587f32926958d72ea7cd97fef551a89d550921ebee82924752f", "overall_ocr_res": "https://pplines-online.bj.bcebos.com/deploy/official/paddleocr/structure-v3-online//925a28c2-7226-47d3-a892-082bea01033b/overall_ocr_res_0.jpg?authorization=bce-auth-v1%2FALTAKDN8mY5KlNI7zaRpLmOqrw%2F2026-06-19T02%3A18%3A26Z%2F-1%2F%2F92993f565dee0dc9ca087d20df59b1a1a0db3d857c23ab9ed342fc5e96a969f0", "layout_order_res": "https://pplines-online.bj.bcebos.com/deploy/official/paddleocr/structure-v3-online//925a28c2-7226-47d3-a892-082bea01033b/layout_order_res_0.jpg?authorization=bce-auth-v1%2FALTAKDN8mY5KlNI7zaRpLmOqrw%2F2026-06-19T02%3A18%3A26Z%2F-1%2F%2F63d7030e1c8099f5a5c4339fdc1b23508a2371982c9be2661c43419722079207"}, "inputImage": "https://pplines-online.bj.bcebos.com/deploy/official/paddleocr/structure-v3-online//925a28c2-7226-47d3-a892-082bea01033b/input_img_0.jpg?authorization=bce-auth-v1%2FALTAKDN8mY5KlNI7zaRpLmOqrw%2F2026-06-19T02%3A18%3A26Z%2F-1%2F%2F55647d9e3639ee8c61b5aedad273596729b43d5c56e8b5a3de1f2c8b7092f04f"}], "dataInfo": {"width": 1931, "height": 2588, "type": "image"}, "ocrResults": [{"prunedResult": {"model_settings": {"use_doc_preprocessor": false, "use_textline_orientation": true}, "dt_polys": [[[898, 222], [1176, 222], [1176, 292], [898, 292]], [[408, 352], [1744, 355], [1744, 399], [408, 396]], [[326, 417], [551, 417], [551, 465], [326, 465]], [[407, 482], [1745, 479], [1745, 523], [407, 526]], [[327, 547], [1745, 541], [1745, 585], [327, 591]], [[328, 612], [1436, 608], [1436, 652], [328, 656]], [[144, 678], [238, 678], [238, 873], [144, 873]], [[393, 673], [577, 673], [577, 722], [393, 722]], [[397, 739], [1230, 735], [1230, 779], [397, 783]], [[1152, 799], [1478, 795], [1479, 840], [1153, 844]], [[153, 960], [234, 959], [236, 1351], [155, 1351]], [[169, 1943], [229, 1943], [229, 2064], [169, 2064]]], "text_det_params": {"limit_side_len": 736, "limit_type": "min", "thresh": 0.3, "max_side_limit": 4000, "box_thresh": 0.6, "unclip_ratio": 1.5}, "text_type": "general", "textline_orientation_angles": [0, 0, 0, 0, 0, 0, 0, 0, 0, 0, 0, 0], "text_rec_score_thresh": 0.0, "return_word_box": false, "rec_texts": ["下营村", "下营村，为洛宁县（旧名永宁县）河底镇的一个建制村，旧名营里村，国营二七", "五处所在地。", "流芳公后裔由渑池坻坞先迁永宁县城。数世后，世科、世登两兄弟迁下营村，世", "登子六（前五子世系未详），其第六子国敬，有子四：长居宜阳县韩城镇东官庄，次居", "杨坡、西官庄，四居杜家阙，三仍居下营。十五世前据朝宦墓碑补。", "渑池", "其世系为：", "流芳公—失传—失传—失传—失传—失传—世科", "世登一国敬一朝宦", "杜氏宗谱", "二三九"], "rec_scores": [0.9987604022026062, 0.9895967841148376, 0.9994428157806396, 0.9756117463111877, 0.9861790537834167, 0.9864251017570496, 0.8682790994644165, 0.9966435432434082, 0.9176371693611145, 0.8924490213394165, 0.9909384250640869, 0.9895793795585632], "rec_polys": [[[898, 222], [1176, 222], [1176, 292], [898, 292]], [[408, 352], [1744, 355], [1744, 399], [408, 396]], [[326, 417], [551, 417], [551, 465], [326, 465]], [[407, 482], [1745, 479], [1745, 523], [407, 526]], [[327, 547], [1745, 541], [1745, 585], [327, 591]], [[328, 612], [1436, 608], [1436, 652], [328, 656]], [[144, 678], [238, 678], [238, 873], [144, 873]], [[393, 673], [577, 673], [577, 722], [393, 722]], [[397, 739], [1230, 735], [1230, 779], [397, 783]], [[1152, 799], [1478, 795], [1479, 840], [1153, 844]], [[153, 960], [234, 959], [236, 1351], [155, 1351]], [[169, 1943], [229, 1943], [229, 2064], [169, 2064]]], "rec_boxes": [[898, 222, 1176, 292], [408, 352, 1744, 399], [326, 417, 551, 465], [407, 479, 1745, 526], [327, 541, 1745, 591], [328, 608, 1436, 656], [144, 678, 238, 873], [393, 673, 577, 722], [397, 735, 1230, 783], [1152, 795, 1479, 844], [153, 959, 236, 1351], [169, 1943, 229, 2064]]}, "ocrImage": "https://pplines-online.bj.bcebos.com/deploy/official/paddleocr/structure-v3-online//925a28c2-7226-47d3-a892-082bea01033b/overall_ocr_res_0.jpg?authorization=bce-auth-v1%2FALTAKDN8mY5KlNI7zaRpLmOqrw%2F2026-06-19T02%3A18%3A26Z%2F-1%2F%2F92993f565dee0dc9ca087d20df59b1a1a0db3d857c23ab9ed342fc5e96a969f0", "inputImage": "https://pplines-online.bj.bcebos.com/deploy/official/paddleocr/structure-v3-online//925a28c2-7226-47d3-a892-082bea01033b/input_img_0.jpg?authorization=bce-auth-v1%2FALTAKDN8mY5KlNI7zaRpLmOqrw%2F2026-06-19T02%3A18%3A26Z%2F-1%2F%2F55647d9e3639ee8c61b5aedad273596729b43d5c56e8b5a3de1f2c8b7092f04f"}], "preprocessedImages": ["https://pplines-online.bj.bcebos.com/deploy/official/paddleocr/structure-v3-online//925a28c2-7226-47d3-a892-082bea01033b/preprocessed_img_0.jpg?authorization=bce-auth-v1%2FALTAKDN8mY5KlNI7zaRpLmOqrw%2F2026-06-19T02%3A18%3A27Z%2F-1%2F%2Fbdebe42dafebac944752b11ff4935c0dd4e2ead00a9eede6d2ae514aa4b68c42"]}