{"layoutParsingResults": [{"prunedResult": {"page_count": null, "width": 1945, "height": 2641, "model_settings": {"use_doc_preprocessor": false, "use_seal_recognition": true, "use_table_recognition": true, "use_formula_recognition": true, "use_chart_recognition": false, "use_region_detection": true, "format_block_content": false, "markdown_ignore_labels": ["number", "footnote", "header", "header_image", "footer", "footer_image", "aside_text"]}, "parsing_res_list": [{"block_label": "paragraph_title", "block_content": "渑池杜氏宗谱", "block_bbox": [120, 703, 196, 1371], "block_id": 0, "block_order": 1}, {"block_label": "text", "block_content": "三八三", "block_bbox": [126, 2000, 176, 2115], "block_id": 1, "block_order": 2}, {"block_label": "text", "block_content": "邑生员杜星五撰文并书丹\n本村以及西坡共珍\n\n时嘉庆十七年岁次壬申一阳月\n", "block_bbox": [373, 238, 905, 403], "block_id": 2, "block_order": 3}, {"block_label": "paragraph_title", "block_content": "永垂不朽", "block_bbox": [375, 479, 545, 521], "block_id": 3, "block_order": 4}, {"block_label": "paragraph_title", "block_content": "钦赐耆老杜公讳廷学之墓", "block_bbox": [375, 539, 830, 583], "block_id": 4, "block_order": 5}, {"block_label": "image", "block_content": "茶\n\n，嗜\n\n同，侄\n\n后迁后\n\n皇\n\n", "block_bbox": [1224, 380, 1744, 2424], "block_id": 5, "block_order": null}, {"block_label": "text", "block_content": "修德承继。公卒，祖茔地狭，同葬于此，是为记。", "block_bbox": [290, 600, 1330, 764], "block_id": 6, "block_order": 6}, {"block_label": "text", "block_content": "道光陆年岁次丙戌夏月吉日立", "block_bbox": [374, 782, 907, 823], "block_id": 7, "block_order": 7}, {"block_label": "paragraph_title", "block_content": "清故处士杜公讳金龙配氏墓", "block_bbox": [376, 902, 884, 942], "block_id": 8, "block_order": 8}, {"block_label": "text", "block_content": "寨，及杜金龙事迹等）\n", "block_bbox": [293, 963, 1329, 1064], "block_id": 9, "block_order": 9}, {"block_label": "text", "block_content": "陕郡增生□□口□口顿首拜□邑庠生春□口口鹿鸣顿首拜□子万贵暨孙□口立\n大清咸丰元年岁次辛亥三月注：此碑在王都村老寨杜氏祖茔。", "block_bbox": [375, 1082, 969, 1371], "block_id": 10, "block_order": 10}, {"block_label": "paragraph_title", "block_content": "重修关帝庙环抱关台金妆神像碑记", "block_bbox": [378, 1446, 991, 1489], "block_id": 11, "block_order": 11}, {"block_label": "text", "block_content": "兹村直午，旧有关帝庙一座、献殿三间，不知创自何代。至乾隆年间，有耆老杜君讳允惠、允举，起而重修，有碑可考。历年久远，庙貌神像有风雨剥落之虞，适有耆老卫君口口侯君振福杜君口口等，目睹心惨，募化赀财八十千文，竭力董率。俾催残之景象，顿为改观；赫耀之声灵，俨乎可接。功成，属文于余。余思圣帝，忠著汉室，义结桃园，凛凛乎忠肝义胆，且令乎千载以下，顽者廉懦者立，是大有裨于名教也。至于至大至刚，气直塞乎天地；允文允武，功常炳若日星。前人之述备矣，非浅见寡闻者所以赞其万一也。然亦有不容已于一赞者，亦天籁之自鸣也。因作俚句曰：峨峨古庙赖谁修？物换星移几度秋。鸟革翬飞经后进，松苍柏翠想前猷。檐牙高啄凌河汉，台榭轩翔射斗牛。千载英灵今宛在，", "block_bbox": [290, 1506, 1185, 2405], "block_id": 12, "block_order": 12}], "layout_det_res": {"boxes": [{"cls_id": 2, "label": "text", "score": 0.9794883728027344, "coordinate": [290.79693603515625, 1506.263671875, 1185.873046875, 2405.650634765625]}, {"cls_id": 2, "label": "text", "score": 0.9365056753158569, "coordinate": [290.52716064453125, 600.582763671875, 1330.3603515625, 764.592041015625]}, {"cls_id": 2, "label": "text", "score": 0.8767238855361938, "coordinate": [373.461669921875, 238.00360107421875, 905.349365234375, 403.23358154296875]}, {"cls_id": 2, "label": "text", "score": 0.8707234263420105, "coordinate": [293.67425537109375, 963.834228515625, 1329.19921875, 1064.926025390625]}, {"cls_id": 2, "label": "text", "score": 0.848759651184082, "coordinate": [374.79364013671875, 782.2429809570312, 907.9669799804688, 823.2546997070312]}, {"cls_id": 0, "label": "paragraph_title", "score": 0.7581124305725098, "coordinate": [376.281982421875, 902.1854858398438, 884.869140625, 942.7616577148438]}, {"cls_id": 0, "label": "paragraph_title", "score": 0.7004144191741943, "coordinate": [378.5626525878906, 1446.6678466796875, 991.3258056640625, 1489.1197509765625]}, {"cls_id": 0, "label": "paragraph_title", "score": 0.6905432939529419, "coordinate": [375.829833984375, 479.65277099609375, 545.0151977539062, 521.7930297851562]}, {"cls_id": 2, "label": "text", "score": 0.6887302994728088, "coordinate": [378.2290344238281, 1204.900146484375, 707.6865234375, 1244.965087890625]}, {"cls_id": 2, "label": "text", "score": 0.6668908596038818, "coordinate": [379.60406494140625, 1327.2213134765625, 968.3729858398438, 1369.2662353515625]}, {"cls_id": 2, "label": "text", "score": 0.6392197012901306, "coordinate": [378.4498291015625, 1144.1004638671875, 910.2318115234375, 1186.4403076171875]}, {"cls_id": 1, "label": "image", "score": 0.6381620168685913, "coordinate": [1224.6632080078125, 380.853759765625, 1744.6971435546875, 2424.08056640625]}, {"cls_id": 2, "label": "text", "score": 0.636174201965332, "coordinate": [378.1063232421875, 1265.0162353515625, 865.1246337890625, 1307.3719482421875]}, {"cls_id": 2, "label": "text", "score": 0.5979966521263123, "coordinate": [376.73480224609375, 1082.6201171875, 909.8892211914062, 1126.203125]}, {"cls_id": 2, "label": "text", "score": 0.5500632524490356, "coordinate": [375.9271240234375, 1082.193603515625, 969.8619384765625, 1371.316650390625]}, {"cls_id": 0, "label": "paragraph_title", "score": 0.5203310251235962, "coordinate": [375.34722900390625, 539.9690551757812, 830.8285522460938, 583.2660522460938]}, {"cls_id": 2, "label": "text", "score": 0.4678056240081787, "coordinate": [126.23361206054688, 2000.507080078125, 176.89254760742188, 2115.906005859375]}, {"cls_id": 2, "label": "text", "score": 0.4396243691444397, "coordinate": [375.79705810546875, 299.2728576660156, 708.8140258789062, 341.7001037597656]}, {"cls_id": 2, "label": "text", "score": 0.4216384291648865, "coordinate": [377.44366455078125, 237.62266540527344, 832.3652954101562, 283.53759765625]}, {"cls_id": 2, "label": "text", "score": 0.4105597734451294, "coordinate": [375.27276611328125, 360.2189636230469, 904.7565307617188, 403.4533996582031]}, {"cls_id": 0, "label": "paragraph_title", "score": 0.3877641558647156, "coordinate": [120.46139526367188, 703.2495727539062, 196.05996704101562, 1371.56787109375]}]}, "overall_ocr_res": {"model_settings": {"use_doc_preprocessor": false, "use_textline_orientation": true}, "dt_polys": [[[381, 238], [830, 242], [830, 286], [380, 281]], [[380, 298], [709, 300], [708, 345], [380, 343]], [[379, 358], [906, 363], [905, 407], [378, 402]], [[1520, 451], [1641, 425], [1665, 539], [1544, 564]], [[379, 479], [544, 479], [544, 525], [379, 525]], [[383, 542], [826, 546], [826, 584], [383, 580]], [[379, 600], [1330, 600], [1330, 647], [379, 647]], [[301, 661], [1330, 661], [1330, 707], [301, 707]], [[109, 693], [205, 693], [205, 889], [109, 889]], [[301, 720], [1167, 724], [1167, 769], [301, 765]], [[381, 781], [905, 786], [905, 826], [381, 822]], [[383, 902], [881, 905], [881, 945], [383, 942]], [[404, 963], [1329, 963], [1329, 1012], [404, 1012]], [[118, 982], [203, 983], [200, 1376], [114, 1376]], [[300, 1021], [697, 1023], [696, 1067], [300, 1065]], [[381, 1081], [907, 1086], [906, 1130], [380, 1124]], [[384, 1143], [906, 1148], [906, 1188], [384, 1184]], [[383, 1204], [706, 1207], [705, 1248], [382, 1245]], [[383, 1265], [863, 1268], [863, 1309], [383, 1306]], [[383, 1325], [965, 1330], [964, 1370], [383, 1366]], [[384, 1446], [987, 1452], [986, 1492], [383, 1485]], [[385, 1505], [1184, 1511], [1184, 1554], [385, 1549]], [[302, 1565], [1183, 1573], [1182, 1617], [302, 1609]], [[1442, 1562], [1498, 1562], [1498, 1620], [1442, 1620]], [[304, 1627], [1182, 1633], [1182, 1677], [304, 1670]], [[302, 1686], [1183, 1693], [1182, 1737], [302, 1730]], [[302, 1747], [1178, 1752], [1178, 1797], [302, 1792]], [[301, 1810], [1180, 1814], [1180, 1857], [301, 1852]], [[301, 1868], [1181, 1872], [1181, 1920], [301, 1916]], [[302, 1932], [1180, 1936], [1180, 1981], [302, 1977]], [[121, 1996], [183, 1996], [183, 2123], [121, 2123]], [[301, 1992], [1183, 1999], [1182, 2046], [301, 2038]], [[302, 2054], [1182, 2061], [1182, 2105], [302, 2098]], [[300, 2114], [1183, 2121], [1182, 2168], [300, 2161]], [[300, 2178], [1180, 2186], [1179, 2229], [300, 2221]], [[302, 2236], [1181, 2243], [1180, 2288], [302, 2281]], [[300, 2296], [1180, 2303], [1180, 2349], [300, 2342]], [[300, 2355], [1177, 2366], [1176, 2412], [300, 2402]], [[1224, 599], [1332, 599], [1332, 647], [1224, 647]], [[1224, 661], [1331, 661], [1331, 707], [1224, 707]], [[1224, 957], [1332, 957], [1332, 1012], [1224, 1012]]], "text_det_params": {"limit_side_len": 736, "limit_type": "min", "thresh": 0.3, "max_side_limit": 4000, "box_thresh": 0.6, "unclip_ratio": 1.5}, "text_type": "general", "textline_orientation_angles": [0, 0, 0, 0, 0, 0, 0, 0, 0, 0, 0, 0, 0, 0, 0, 0, 0, 0, 0, 0, 0, 0, 0, 0, 0, 0, 0, 0, 0, 0, 0, 0, 0, 0, 0, 0, 0, 0], "text_rec_score_thresh": 0.0, "return_word_box": false, "rec_texts": ["邑生员杜星五撰文并书丹", "本村以及西坡共珍", "时嘉庆十七年岁次壬申一阳月", "茶", "永垂不朽", "钦赐耆老杜公讳廷学之墓", "", "", "渑池", "修德承继。公卒，祖茔地狭，同葬于此，是为记。", "道光陆年岁次丙戌夏月吉日立", "清故处士杜公讳金龙配氏墓", "", "杜氏宗谱", "寨，及杜金龙事迹等）", "陕郡增生□□口□口顿首拜□", "邑庠生春□口口鹿鸣顿首拜□", "子万贵暨孙□口立", "大清咸丰元年岁次辛亥三月", "注：此碑在王都村老寨杜氏祖茔。", "重修关帝庙环抱关台金妆神像碑记", "兹村直午，旧有关帝庙一座、献殿三间，不", "知创自何代。至乾隆年间，有耆老杜君讳允惠、", "皇", "允举，起而重修，有碑可考。历年久远，庙貌神", "像有风雨剥落之虞，适有耆老卫君口口侯君振福", "杜君口口等，目睹心惨，募化赀财八十千文，", "竭力董率。俾催残之景象，顿为改观；赫耀之声", "灵，俨乎可接。功成，属文于余。余思圣帝，忠", "著汉室，义结桃园，凛凛乎忠肝义胆，且令乎千", "三八三", "载以下，顽者廉懦者立，是大有裨于名教也。至", "于至大至刚，气直塞乎天地；允文允武，功常炳", "若日星。前人之述备矣，非浅见寡闻者所以赞其", "万一也。然亦有不容已于一赞者，亦天籁之自鸣", "也。因作俚句曰：峨峨古庙赖谁修？物换星移几", "度秋。鸟革翬飞经后进，松苍柏翠想前猷。檐牙", "高啄凌河汉，台榭轩翔射斗牛。千载英灵今宛在，", "，嗜", "同，侄", "后迁后"], "rec_scores": [0.9946610927581787, 0.9984827041625977, 0.9977806806564331, 0.15615501999855042, 0.9997031688690186, 0.9957190155982971, 0.9902409911155701, 0.9809233546257019, 0.8822759389877319, 0.9746652841567993, 0.9981259107589722, 0.9974210858345032, 0.9892547130584717, 0.9854010343551636, 0.9885627627372742, 0.8186644315719604, 0.8626804947853088, 0.9335981011390686, 0.9958767294883728, 0.9599062204360962, 0.9987739324569702, 0.9938594698905945, 0.9904186725616455, 0.17834748327732086, 0.9951145648956299, 0.9724410176277161, 0.9383529424667358, 0.9963641166687012, 0.9963299036026001, 0.9958905577659607, 0.9975069165229797, 0.9917885661125183, 0.9910075664520264, 0.9980796575546265, 0.997731626033783, 0.9638890027999878, 0.9660146832466125, 0.9901577234268188, 0.8825956583023071, 0.8790251612663269, 0.9015688300132751], "rec_polys": [[[381, 238], [830, 242], [830, 286], [380, 281]], [[380, 298], [709, 300], [708, 345], [380, 343]], [[379, 358], [906, 363], [905, 407], [378, 402]], [[1520, 451], [1641, 425], [1665, 539], [1544, 564]], [[379, 479], [544, 479], [544, 525], [379, 525]], [[383, 542], [826, 546], [826, 584], [383, 580]], [[379, 600], [1330, 600], [1330, 647], [379, 647]], [[301, 661], [1330, 661], [1330, 707], [301, 707]], [[109, 693], [205, 693], [205, 889], [109, 889]], [[301, 720], [1167, 724], [1167, 769], [301, 765]], [[381, 781], [905, 786], [905, 826], [381, 822]], [[383, 902], [881, 905], [881, 945], [383, 942]], [[404, 963], [1329, 963], [1329, 1012], [404, 1012]], [[118, 982], [203, 983], [200, 1376], [114, 1376]], [[300, 1021], [697, 1023], [696, 1067], [300, 1065]], [[381, 1081], [907, 1086], [906, 1130], [380, 1124]], [[384, 1143], [906, 1148], [906, 1188], [384, 1184]], [[383, 1204], [706, 1207], [705, 1248], [382, 1245]], [[383, 1265], [863, 1268], [863, 1309], [383, 1306]], [[383, 1325], [965, 1330], [964, 1370], [383, 1366]], [[384, 1446], [987, 1452], [986, 1492], [383, 1485]], [[385, 1505], [1184, 1511], [1184, 1554], [385, 1549]], [[302, 1565], [1183, 1573], [1182, 1617], [302, 1609]], [[1442, 1562], [1498, 1562], [1498, 1620], [1442, 1620]], [[304, 1627], [1182, 1633], [1182, 1677], [304, 1670]], [[302, 1686], [1183, 1693], [1182, 1737], [302, 1730]], [[302, 1747], [1178, 1752], [1178, 1797], [302, 1792]], [[301, 1810], [1180, 1814], [1180, 1857], [301, 1852]], [[301, 1868], [1181, 1872], [1181, 1920], [301, 1916]], [[302, 1932], [1180, 1936], [1180, 1981], [302, 1977]], [[121, 1996], [183, 1996], [183, 2123], [121, 2123]], [[301, 1992], [1183, 1999], [1182, 2046], [301, 2038]], [[302, 2054], [1182, 2061], [1182, 2105], [302, 2098]], [[300, 2114], [1183, 2121], [1182, 2168], [300, 2161]], [[300, 2178], [1180, 2186], [1179, 2229], [300, 2221]], [[302, 2236], [1181, 2243], [1180, 2288], [302, 2281]], [[300, 2296], [1180, 2303], [1180, 2349], [300, 2342]], [[300, 2355], [1177, 2366], [1176, 2412], [300, 2402]], [[1224, 599], [1332, 599], [1332, 647], [1224, 647]], [[1224, 661], [1331, 661], [1331, 707], [1224, 707]], [[1224, 957], [1332, 957], [1332, 1012], [1224, 1012]]], "rec_boxes": [[380.0, 238.0, 830.0, 286.0], [380.0, 298.0, 709.0, 345.0], [378.0, 358.0, 906.0, 407.0], [1520.0, 425.0, 1665.0, 564.0], [379.0, 479.0, 544.0, 525.0], [383.0, 542.0, 826.0, 584.0], [379.0, 600.0, 1330.0, 647.0], [301.0, 661.0, 1330.3603515625, 707.0], [109.0, 693.0, 205.0, 889.0], [301.0, 720.0, 1167.0, 769.0], [381.0, 781.0, 905.0, 826.0], [383.0, 902.0, 881.0, 945.0], [404.0, 963.834228515625, 1329.19921875, 1012.0], [114.0, 982.0, 203.0, 1376.0], [300.0, 1021.0, 697.0, 1067.0], [380.0, 1081.0, 907.0, 1130.0], [384.0, 1143.0, 906.0, 1188.0], [382.0, 1204.0, 706.0, 1248.0], [383.0, 1265.0, 863.0, 1309.0], [383.0, 1325.0, 965.0, 1370.0], [383.0, 1446.0, 987.0, 1492.0], [385.0, 1505.0, 1184.0, 1554.0], [302.0, 1565.0, 1183.0, 1617.0], [1442.0, 1562.0, 1498.0, 1620.0], [304.0, 1627.0, 1182.0, 1677.0], [302.0, 1686.0, 1183.0, 1737.0], [302.0, 1747.0, 1178.0, 1797.0], [301.0, 1810.0, 1180.0, 1857.0], [301.0, 1868.0, 1181.0, 1920.0], [302.0, 1932.0, 1180.0, 1981.0], [121.0, 1996.0, 183.0, 2123.0], [301.0, 1992.0, 1183.0, 2046.0], [302.0, 2054.0, 1182.0, 2105.0], [300.0, 2114.0, 1183.0, 2168.0], [300.0, 2178.0, 1180.0, 2229.0], [302.0, 2236.0, 1181.0, 2288.0], [300.0, 2296.0, 1180.0, 2349.0], [300.0, 2355.0, 1177.0, 2412.0], [1224.6632080078125, 599.0, 1332.0, 647.0], [1224.6632080078125, 661.0, 1331.0, 707.0], [1224.6632080078125, 957.0, 1332.0, 1012.0]]}}, "markdown": {"text": "## 渑池杜氏宗谱\n\n三八三\n\n邑生员杜星五撰文并书丹\n\n本村以及西坡共珍\n\n时嘉庆十七年岁次壬申一阳月\n\n\n\n## 永垂不朽\n\n## 钦赐耆老杜公讳廷学之墓\n\n<div style=\"text-align: center;\"><img src=\"imgs/img_in_image_box_1224_380_1744_2424.jpg\" alt=\"Image\" width=\"26%\" /></div>\n\n\n修德承继。公卒，祖茔地狭，同葬于此，是为记。\n\n道光陆年岁次丙戌夏月吉日立\n\n## 清故处士杜公讳金龙配氏墓\n\n寨，及杜金龙事迹等）\n\n\n\n陕郡增生□□口□口顿首拜□邑庠生春□口口鹿鸣顿首拜□子万贵暨孙□口立\n\n大清咸丰元年岁次辛亥三月注：此碑在王都村老寨杜氏祖茔。\n\n## 重修关帝庙环抱关台金妆神像碑记\n\n兹村直午，旧有关帝庙一座、献殿三间，不知创自何代。至乾隆年间，有耆老杜君讳允惠、允举，起而重修，有碑可考。历年久远，庙貌神像有风雨剥落之虞，适有耆老卫君口口侯君振福杜君口口等，目睹心惨，募化赀财八十千文，竭力董率。俾催残之景象，顿为改观；赫耀之声灵，俨乎可接。功成，属文于余。余思圣帝，忠著汉室，义结桃园，凛凛乎忠肝义胆，且令乎千载以下，顽者廉懦者立，是大有裨于名教也。至于至大至刚，气直塞乎天地；允文允武，功常炳若日星。前人之述备矣，非浅见寡闻者所以赞其万一也。然亦有不容已于一赞者，亦天籁之自鸣也。因作俚句曰：峨峨古庙赖谁修？物换星移几度秋。鸟革翬飞经后进，松苍柏翠想前猷。檐牙高啄凌河汉，台榭轩翔射斗牛。千载英灵今宛在，", "isStart": false, "isEnd": false, "images": {"imgs/img_in_image_box_1224_380_1744_2424.jpg": "https://pplines-online.bj.bcebos.com/deploy/official/paddleocr/structure-v3-online//5781bcf5-6768-4bc8-a9e1-c68114fdbc50/markdown_0/imgs/img_in_image_box_1224_380_1744_2424.jpg?authorization=bce-auth-v1%2FALTAKDN8mY5KlNI7zaRpLmOqrw%2F2026-06-19T02%3A32%3A18Z%2F-1%2F%2Ffaa09d014be902130b2ff59fa42c15577441f61dc1d0c6b04a3d40be1aa02e58"}}, "outputImages": {"layout_det_res": "https://pplines-online.bj.bcebos.com/deploy/official/paddleocr/structure-v3-online//5781bcf5-6768-4bc8-a9e1-c68114fdbc50/layout_det_res_0.jpg?authorization=bce-auth-v1%2FALTAKDN8mY5KlNI7zaRpLmOqrw%2F2026-06-19T02%3A32%3A20Z%2F-1%2F%2F878f547a849a8f37d11d77c78edcb22f1b1fb9ca9098351e758c9ce346bee175", "region_det_res": "https://pplines-online.bj.bcebos.com/deploy/official/paddleocr/structure-v3-online//5781bcf5-6768-4bc8-a9e1-c68114fdbc50/region_det_res_0.jpg?authorization=bce-auth-v1%2FALTAKDN8mY5KlNI7zaRpLmOqrw%2F2026-06-19T02%3A32%3A20Z%2F-1%2F%2F1fadf77f6f15a288fac07ec34613096d75bd1e9edbab6b2aed8f72a50b8bf06f", "overall_ocr_res": "https://pplines-online.bj.bcebos.com/deploy/official/paddleocr/structure-v3-online//5781bcf5-6768-4bc8-a9e1-c68114fdbc50/overall_ocr_res_0.jpg?authorization=bce-auth-v1%2FALTAKDN8mY5KlNI7zaRpLmOqrw%2F2026-06-19T02%3A32%3A20Z%2F-1%2F%2F028f023ebc02f54c6acf002270112b92671f84b203198f90812fcdec58d410c4", "layout_order_res": "https://pplines-online.bj.bcebos.com/deploy/official/paddleocr/structure-v3-online//5781bcf5-6768-4bc8-a9e1-c68114fdbc50/layout_order_res_0.jpg?authorization=bce-auth-v1%2FALTAKDN8mY5KlNI7zaRpLmOqrw%2F2026-06-19T02%3A32%3A20Z%2F-1%2F%2F968997994e3a277d980f5e0a4e75b7e2c80c917d161be3232b6eaeda438c4196"}, "inputImage": "https://pplines-online.bj.bcebos.com/deploy/official/paddleocr/structure-v3-online//5781bcf5-6768-4bc8-a9e1-c68114fdbc50/input_img_0.jpg?authorization=bce-auth-v1%2FALTAKDN8mY5KlNI7zaRpLmOqrw%2F2026-06-19T02%3A32%3A19Z%2F-1%2F%2Fb9fef8671d8d80293190b45ea2d029e995fc5479b42007faaac4f1840f509301"}], "dataInfo": {"width": 1945, "height": 2641, "type": "image"}, "ocrResults": [{"prunedResult": {"model_settings": {"use_doc_preprocessor": false, "use_textline_orientation": true}, "dt_polys": [[[381, 238], [830, 242], [830, 286], [380, 281]], [[380, 298], [709, 300], [708, 345], [380, 343]], [[379, 358], [906, 363], [905, 407], [378, 402]], [[1520, 451], [1641, 425], [1665, 539], [1544, 564]], [[379, 479], [544, 479], [544, 525], [379, 525]], [[383, 542], [826, 546], [826, 584], [383, 580]], [[379, 600], [1330, 600], [1330, 647], [379, 647]], [[301, 661], [1330, 661], [1330, 707], [301, 707]], [[109, 693], [205, 693], [205, 889], [109, 889]], [[301, 720], [1167, 724], [1167, 769], [301, 765]], [[381, 781], [905, 786], [905, 826], [381, 822]], [[383, 902], [881, 905], [881, 945], [383, 942]], [[404, 963], [1329, 963], [1329, 1012], [404, 1012]], [[118, 982], [203, 983], [200, 1376], [114, 1376]], [[300, 1021], [697, 1023], [696, 1067], [300, 1065]], [[381, 1081], [907, 1086], [906, 1130], [380, 1124]], [[384, 1143], [906, 1148], [906, 1188], [384, 1184]], [[383, 1204], [706, 1207], [705, 1248], [382, 1245]], [[383, 1265], [863, 1268], [863, 1309], [383, 1306]], [[383, 1325], [965, 1330], [964, 1370], [383, 1366]], [[384, 1446], [987, 1452], [986, 1492], [383, 1485]], [[385, 1505], [1184, 1511], [1184, 1554], [385, 1549]], [[302, 1565], [1183, 1573], [1182, 1617], [302, 1609]], [[1442, 1562], [1498, 1562], [1498, 1620], [1442, 1620]], [[304, 1627], [1182, 1633], [1182, 1677], [304, 1670]], [[302, 1686], [1183, 1693], [1182, 1737], [302, 1730]], [[302, 1747], [1178, 1752], [1178, 1797], [302, 1792]], [[301, 1810], [1180, 1814], [1180, 1857], [301, 1852]], [[301, 1868], [1181, 1872], [1181, 1920], [301, 1916]], [[302, 1932], [1180, 1936], [1180, 1981], [302, 1977]], [[121, 1996], [183, 1996], [183, 2123], [121, 2123]], [[301, 1992], [1183, 1999], [1182, 2046], [301, 2038]], [[302, 2054], [1182, 2061], [1182, 2105], [302, 2098]], [[300, 2114], [1183, 2121], [1182, 2168], [300, 2161]], [[300, 2178], [1180, 2186], [1179, 2229], [300, 2221]], [[302, 2236], [1181, 2243], [1180, 2288], [302, 2281]], [[300, 2296], [1180, 2303], [1180, 2349], [300, 2342]], [[300, 2355], [1177, 2366], [1176, 2412], [300, 2402]], [[1224, 599], [1332, 599], [1332, 647], [1224, 647]], [[1224, 661], [1331, 661], [1331, 707], [1224, 707]], [[1224, 957], [1332, 957], [1332, 1012], [1224, 1012]]], "text_det_params": {"limit_side_len": 736, "limit_type": "min", "thresh": 0.3, "max_side_limit": 4000, "box_thresh": 0.6, "unclip_ratio": 1.5}, "text_type": "general", "textline_orientation_angles": [0, 0, 0, 0, 0, 0, 0, 0, 0, 0, 0, 0, 0, 0, 0, 0, 0, 0, 0, 0, 0, 0, 0, 0, 0, 0, 0, 0, 0, 0, 0, 0, 0, 0, 0, 0, 0, 0], "text_rec_score_thresh": 0.0, "return_word_box": false, "rec_texts": ["邑生员杜星五撰文并书丹", "本村以及西坡共珍", "时嘉庆十七年岁次壬申一阳月", "茶", "永垂不朽", "钦赐耆老杜公讳廷学之墓", "", "", "渑池", "修德承继。公卒，祖茔地狭，同葬于此，是为记。", "道光陆年岁次丙戌夏月吉日立", "清故处士杜公讳金龙配氏墓", "", "杜氏宗谱", "寨，及杜金龙事迹等）", "陕郡增生□□口□口顿首拜□", "邑庠生春□口口鹿鸣顿首拜□", "子万贵暨孙□口立", "大清咸丰元年岁次辛亥三月", "注：此碑在王都村老寨杜氏祖茔。", "重修关帝庙环抱关台金妆神像碑记", "兹村直午，旧有关帝庙一座、献殿三间，不", "知创自何代。至乾隆年间，有耆老杜君讳允惠、", "皇", "允举，起而重修，有碑可考。历年久远，庙貌神", "像有风雨剥落之虞，适有耆老卫君口口侯君振福", "杜君口口等，目睹心惨，募化赀财八十千文，", "竭力董率。俾催残之景象，顿为改观；赫耀之声", "灵，俨乎可接。功成，属文于余。余思圣帝，忠", "著汉室，义结桃园，凛凛乎忠肝义胆，且令乎千", "三八三", "载以下，顽者廉懦者立，是大有裨于名教也。至", "于至大至刚，气直塞乎天地；允文允武，功常炳", "若日星。前人之述备矣，非浅见寡闻者所以赞其", "万一也。然亦有不容已于一赞者，亦天籁之自鸣", "也。因作俚句曰：峨峨古庙赖谁修？物换星移几", "度秋。鸟革翬飞经后进，松苍柏翠想前猷。檐牙", "高啄凌河汉，台榭轩翔射斗牛。千载英灵今宛在，", "，嗜", "同，侄", "后迁后"], "rec_scores": [0.9946610927581787, 0.9984827041625977, 0.9977806806564331, 0.15615501999855042, 0.9997031688690186, 0.9957190155982971, 0.9902409911155701, 0.9809233546257019, 0.8822759389877319, 0.9746652841567993, 0.9981259107589722, 0.9974210858345032, 0.9892547130584717, 0.9854010343551636, 0.9885627627372742, 0.8186644315719604, 0.8626804947853088, 0.9335981011390686, 0.9958767294883728, 0.9599062204360962, 0.9987739324569702, 0.9938594698905945, 0.9904186725616455, 0.17834748327732086, 0.9951145648956299, 0.9724410176277161, 0.9383529424667358, 0.9963641166687012, 0.9963299036026001, 0.9958905577659607, 0.9975069165229797, 0.9917885661125183, 0.9910075664520264, 0.9980796575546265, 0.997731626033783, 0.9638890027999878, 0.9660146832466125, 0.9901577234268188, 0.8825956583023071, 0.8790251612663269, 0.9015688300132751], "rec_polys": [[[381, 238], [830, 242], [830, 286], [380, 281]], [[380, 298], [709, 300], [708, 345], [380, 343]], [[379, 358], [906, 363], [905, 407], [378, 402]], [[1520, 451], [1641, 425], [1665, 539], [1544, 564]], [[379, 479], [544, 479], [544, 525], [379, 525]], [[383, 542], [826, 546], [826, 584], [383, 580]], [[379, 600], [1330, 600], [1330, 647], [379, 647]], [[301, 661], [1330, 661], [1330, 707], [301, 707]], [[109, 693], [205, 693], [205, 889], [109, 889]], [[301, 720], [1167, 724], [1167, 769], [301, 765]], [[381, 781], [905, 786], [905, 826], [381, 822]], [[383, 902], [881, 905], [881, 945], [383, 942]], [[404, 963], [1329, 963], [1329, 1012], [404, 1012]], [[118, 982], [203, 983], [200, 1376], [114, 1376]], [[300, 1021], [697, 1023], [696, 1067], [300, 1065]], [[381, 1081], [907, 1086], [906, 1130], [380, 1124]], [[384, 1143], [906, 1148], [906, 1188], [384, 1184]], [[383, 1204], [706, 1207], [705, 1248], [382, 1245]], [[383, 1265], [863, 1268], [863, 1309], [383, 1306]], [[383, 1325], [965, 1330], [964, 1370], [383, 1366]], [[384, 1446], [987, 1452], [986, 1492], [383, 1485]], [[385, 1505], [1184, 1511], [1184, 1554], [385, 1549]], [[302, 1565], [1183, 1573], [1182, 1617], [302, 1609]], [[1442, 1562], [1498, 1562], [1498, 1620], [1442, 1620]], [[304, 1627], [1182, 1633], [1182, 1677], [304, 1670]], [[302, 1686], [1183, 1693], [1182, 1737], [302, 1730]], [[302, 1747], [1178, 1752], [1178, 1797], [302, 1792]], [[301, 1810], [1180, 1814], [1180, 1857], [301, 1852]], [[301, 1868], [1181, 1872], [1181, 1920], [301, 1916]], [[302, 1932], [1180, 1936], [1180, 1981], [302, 1977]], [[121, 1996], [183, 1996], [183, 2123], [121, 2123]], [[301, 1992], [1183, 1999], [1182, 2046], [301, 2038]], [[302, 2054], [1182, 2061], [1182, 2105], [302, 2098]], [[300, 2114], [1183, 2121], [1182, 2168], [300, 2161]], [[300, 2178], [1180, 2186], [1179, 2229], [300, 2221]], [[302, 2236], [1181, 2243], [1180, 2288], [302, 2281]], [[300, 2296], [1180, 2303], [1180, 2349], [300, 2342]], [[300, 2355], [1177, 2366], [1176, 2412], [300, 2402]], [[1224, 599], [1332, 599], [1332, 647], [1224, 647]], [[1224, 661], [1331, 661], [1331, 707], [1224, 707]], [[1224, 957], [1332, 957], [1332, 1012], [1224, 1012]]], "rec_boxes": [[380.0, 238.0, 830.0, 286.0], [380.0, 298.0, 709.0, 345.0], [378.0, 358.0, 906.0, 407.0], [1520.0, 425.0, 1665.0, 564.0], [379.0, 479.0, 544.0, 525.0], [383.0, 542.0, 826.0, 584.0], [379.0, 600.0, 1330.0, 647.0], [301.0, 661.0, 1330.3603515625, 707.0], [109.0, 693.0, 205.0, 889.0], [301.0, 720.0, 1167.0, 769.0], [381.0, 781.0, 905.0, 826.0], [383.0, 902.0, 881.0, 945.0], [404.0, 963.834228515625, 1329.19921875, 1012.0], [114.0, 982.0, 203.0, 1376.0], [300.0, 1021.0, 697.0, 1067.0], [380.0, 1081.0, 907.0, 1130.0], [384.0, 1143.0, 906.0, 1188.0], [382.0, 1204.0, 706.0, 1248.0], [383.0, 1265.0, 863.0, 1309.0], [383.0, 1325.0, 965.0, 1370.0], [383.0, 1446.0, 987.0, 1492.0], [385.0, 1505.0, 1184.0, 1554.0], [302.0, 1565.0, 1183.0, 1617.0], [1442.0, 1562.0, 1498.0, 1620.0], [304.0, 1627.0, 1182.0, 1677.0], [302.0, 1686.0, 1183.0, 1737.0], [302.0, 1747.0, 1178.0, 1797.0], [301.0, 1810.0, 1180.0, 1857.0], [301.0, 1868.0, 1181.0, 1920.0], [302.0, 1932.0, 1180.0, 1981.0], [121.0, 1996.0, 183.0, 2123.0], [301.0, 1992.0, 1183.0, 2046.0], [302.0, 2054.0, 1182.0, 2105.0], [300.0, 2114.0, 1183.0, 2168.0], [300.0, 2178.0, 1180.0, 2229.0], [302.0, 2236.0, 1181.0, 2288.0], [300.0, 2296.0, 1180.0, 2349.0], [300.0, 2355.0, 1177.0, 2412.0], [1224.6632080078125, 599.0, 1332.0, 647.0], [1224.6632080078125, 661.0, 1331.0, 707.0], [1224.6632080078125, 957.0, 1332.0, 1012.0]]}, "ocrImage": "https://pplines-online.bj.bcebos.com/deploy/official/paddleocr/structure-v3-online//5781bcf5-6768-4bc8-a9e1-c68114fdbc50/overall_ocr_res_0.jpg?authorization=bce-auth-v1%2FALTAKDN8mY5KlNI7zaRpLmOqrw%2F2026-06-19T02%3A32%3A20Z%2F-1%2F%2F028f023ebc02f54c6acf002270112b92671f84b203198f90812fcdec58d410c4", "inputImage": "https://pplines-online.bj.bcebos.com/deploy/official/paddleocr/structure-v3-online//5781bcf5-6768-4bc8-a9e1-c68114fdbc50/input_img_0.jpg?authorization=bce-auth-v1%2FALTAKDN8mY5KlNI7zaRpLmOqrw%2F2026-06-19T02%3A32%3A19Z%2F-1%2F%2Fb9fef8671d8d80293190b45ea2d029e995fc5479b42007faaac4f1840f509301"}], "preprocessedImages": ["https://pplines-online.bj.bcebos.com/deploy/official/paddleocr/structure-v3-online//5781bcf5-6768-4bc8-a9e1-c68114fdbc50/preprocessed_img_0.jpg?authorization=bce-auth-v1%2FALTAKDN8mY5KlNI7zaRpLmOqrw%2F2026-06-19T02%3A32%3A20Z%2F-1%2F%2F7e7932ff125b1fb3539a4a3adba0ca47ee1fcf69f3b88cde42927b9747217f58"]}